CIDI-Modulos/SD122-CIRC-DIGITAIS-I/SD122-Task-1/mux_2x1.v
// RTL          -> com portas lógicas
// estrutural   -> com instancias 
// comportamental   -> é o que usa always

// 1ª Parte do Exercício 2
module mux2(a, b, sel, y);
    input a, b, sel;
    output y;

assign y = sel ? a : b; 

endmodule

// 2ª Parte do Exercício 2
module mux3(
   input [1:0] D, sel,
   output y
);

assign y = sel ? D[0] : D[1]; 

endmodule

module mux_est(a, b, sel, y); //estrutural
    input a, b, sel;
    output y;

    wire w1, w2;

    or I1(y,w1,w2);
    and I2(w1,!sel,a);
    and I3(w2, sel,b);

endmodule

module mux_rtl(a, b, sel, y);
    input a, b, sel;
    output y;

    wire n_sel, and1, and2;

    assign n_sel = ~sel;
    assign and1 = a & n_sel;
    assign and2 = sel & b;
    assign y = and1 | and2;

endmodule

/*
    Atividade 3
*/
module mux4_comport(a, b, sel, y); //comportamental 
    input a, b, sel;
    output reg y;

    always@(*) begin
        if(sel == 1'b0)
            y = a;
        else
            y = b;
    end

endmodule

CIDI-Modulos/SD122-CIRC-DIGITAIS-I/SD122-Task-1/mux_2x1_tb.v
`timescale 1ns/1ps
`include "mux_2x1.v"

module mux_2x1_tb;

    //reg a, b, sel; // 1ª Parte
    reg [1:0]D, sel;
    wire y;

   // 1ª Parte do exercicio 2
   // mux2 mux_2x1_tb(
   //     .a(a), .b(b), .sel(sel),
   //     .y(y)
   // );

   mux3 upp(
    .D(D), .sel(sel), 
    .y(y)
   );

    // 1º Parte
    //always begin #1 a = !a; end
    //always begin #2 b = !b; end

    always begin #1 D[0] = !D[0]; end
    always begin #2 D[1] = !D[1]; end
    always begin #4 sel = !sel; end

    initial begin
      $dumpfile("mux_2x1_tb.vcd");
      $dumpvars(0, mux_2x1_tb);
      // se 1 -> a, 0 -> b
      sel = 1'b0;
      //a = 1'b0;
      //b = 1'b0;
      D = 2'd0;
      #10;
      $finish;

    end

endmodule

CIDI-Modulos/SD122-CIRC-DIGITAIS-I/SD122-Task-1/mux_2x1_tb.vcd
$date
	Sun Nov  2 16:13:46 2025
$end
$version
	Icarus Verilog
$end
$timescale
	1ps
$end
$scope module mux_2x1_tb $end
$var wire 1 ! y $end
$var reg 2 " D [1:0] $end
$var reg 2 # sel [1:0] $end
$scope module upp $end
$var wire 2 $ D [1:0] $end
$var wire 2 % sel [1:0] $end
$var wire 1 ! y $end
$upscope $end
$upscope $end
$enddefinitions $end
#0
$dumpvars
b0 %
b0 $
b0 #
b0 "
0!
$end
#1000
b1 "
b1 $
#2000
1!
b10 "
b10 $
#3000
b11 "
b11 $
#4000
0!
b0 "
b0 $
b1 #
b1 %
#5000
1!
b1 "
b1 $
#6000
0!
b10 "
b10 $
#7000
1!
b11 "
b11 $
#8000
0!
b0 "
b0 $
b0 #
b0 %
#9000
b1 "
b1 $
#10000
1!
b10 "
b10 $
