CIDI-Modulos/SD142-CIRC-DIGITAIS-III/A-302/fifo_8x8_buffer_circular.v
/*
Program: CI Digital T2/2025
Class: Circuito Digitais III
Class-ID: SD142
Advisor: Felipe Rocha 
Advisor-Contact: felipef.rocha@inatel.br
Institute: INATEL - Santa Rita do Sapucaí / MG  
Development: André Bezerra 
Student-Contact: andrefrbezerra@gmail.com
Task-ID: A-301 (A-302)
Type: Laboratory
Data: febuary, 2 2026
*/

`timescale 1 ns / 1 ps
 
module fifo_8x8_buffer_circular #(
	parameter WIDTH = 8
)(
    input clk, reset, rd, wr,
    input [WIDTH-1 : 0] w_data,
    
    output full, empty,
    output reg [WIDTH-1 : 0] r_data
);

    reg [2:0] w_ptr, r_ptr;
    reg [WIDTH-1 : 0] fifo_8x8_buffer [WIDTH-1 : 0];

    wire full_internal, empty_internal;  

	// [X] Checar se o pointer está na mesma posição a menos que o pointer da escrita
    assign full_internal = ((w_ptr + 1) % WIDTH) == r_ptr; 
    assign full = full_internal;
    
    // [X] Checa se estão na mesma posição
    assign empty_internal = w_ptr == r_ptr; 
    assign empty = empty_internal;

    always @(posedge clk or posedge reset) begin
        if (reset) begin
            w_ptr <= 3'b000;
        end else if (wr && !full_internal) begin
        	// [x] Insere o dado no buffer 
            fifo_8x8_buffer[w_ptr] <= w_data; 
            // [x] Atualiza o valor do pointer de escrita de forma circular
            w_ptr <= (w_ptr + 1) % WIDTH; 
        end
    end

    always @(posedge clk or posedge reset) begin
        if (reset) begin
            r_ptr <= 3'b000;
            r_data <= 8'b00000000;
        end else if (rd && !empty_internal) begin
        	//Realiza a leitura do buffer
            r_data <= fifo_8x8_buffer[r_ptr];
            //Atualiza o valor do pointer de leitura de forma circular 
            r_ptr <= (r_ptr + 1) % WIDTH; 
        end
    end

endmodule

CIDI-Modulos/SD142-CIRC-DIGITAIS-III/A-302/fifo_8x8_buffer_circular_tb.v
/*
Program: CI Digital T2/2025
Class: Circuito Digitais III
Class-ID: SD142
Advisor: Felipe Rocha 
Advisor-Contact: felipef.rocha@inatel.br
Institute: INATEL - Santa Rita do Sapucaí / MG  
Development: André Bezerra 
Student-Contact: andrefrbezerra@gmail.com
Task-ID: A-301 (A-302)
Type: TestBench
Data: febuary, 2 2026
*/

`timescale 1 ns / 1 ps

module fifo_8x8_buffer_circular_tb;

	localparam WIDTH = 8; 
	
	reg clk, reset, rd, wr;
	reg [WIDTH-1 : 0] w_data;
	
	wire full, empty;
	wire [WIDTH-1 : 0] r_data;

	fifo_8x8_buffer_circular UUT (
		.clk(clk), .reset(reset), .rd(rd), .wr(wr),
		.w_data(w_data),
		.full(full), .empty(empty),
		.r_data(r_data)
	);
 
	always #5  clk = ! clk;
	
	initial begin
		
		// Specify the VCD file name
		$dumpfile("CIDI-SD142-A301-ff8x8.vcd");
		$dumpvars(0, fifo_8x8_buffer_circular_tb);
			
		$display("|TIME	|STORAGE |DATA (write)|DATA (read) |");
		$monitor("|%0t	|%d	 |%b |%b |", 
			  $time, full, w_data, r_data
		);
		
	end

	integer i; 

	initial begin

		clk <= 1'b0; 
		reset <= 1'b1; 
		wr <= 1'b0; 
		rd <= 1'b0; 

		#5; 
		reset <= 1'b0; 
		wr <= 1'b1; 
		
		i = 0;

		$display("---Writing data---");

		// Task: Processing with 
		for (i = 0; i < WIDTH; i = i+1 ) begin
			@(posedge clk);
			w_data <= $random;
			#5; 
		end

		wr <= 1'b0; 

		// [ ] Analisar possibilidade de resgate por referência (mensagem);
		$display("---Reading Data---");

		rd <= 1'b1;

		for (i = 0; i < WIDTH; i = i+1 ) begin
			@(posedge clk);
			#5; 
		end

		#10;
		$finish;

	end

endmodule

CIDI-Modulos/SD142-CIRC-DIGITAIS-III/A-302/CIDI-SD142-A301-ff8x8.vcd
$date
	Mon Feb 23 14:19:15 2026
$end
$version
	Icarus Verilog
$end
$timescale
	1ps
$end
$scope module fifo_8x8_buffer_circular_tb $end
$var wire 8 ! r_data [7:0] $end
$var wire 1 " full $end
$var wire 1 # empty $end
$var parameter 32 $ WIDTH $end
$var reg 1 % clk $end
$var reg 1 & rd $end
$var reg 1 ' reset $end
$var reg 8 ( w_data [7:0] $end
$var reg 1 ) wr $end
$var integer 32 * i [31:0] $end
$scope module UUT $end
$var wire 1 % clk $end
$var wire 1 # empty $end
$var wire 1 " full $end
$var wire 1 & rd $end
$var wire 1 ' reset $end
$var wire 8 + w_data [7:0] $end
$var wire 1 ) wr $end
$var wire 1 , full_internal $end
$var wire 1 - empty_internal $end
$var parameter 32 . WIDTH $end
$var reg 8 / r_data [7:0] $end
$var reg 3 0 r_ptr [2:0] $end
$var reg 3 1 w_ptr [2:0] $end
$upscope $end
$upscope $end
$enddefinitions $end
$comment Show the parameter values. $end
$dumpall
b1000 .
b1000 $
$end
#0
$dumpvars
b0 1
b0 0
b0 /
1-
0,
bx +
bx *
0)
bx (
1'
0&
0%
1#
0"
b0 !
$end
#5000
1)
0'
b0 *
1%
#10000
0%
#15000
0#
0-
b1 1
b100100 (
b100100 +
1%
#20000
b1 *
0%
#25000
b10 1
b10000001 (
b10000001 +
1%
#30000
b10 *
0%
#35000
b11 1
b1001 (
b1001 +
1%
#40000
b11 *
0%
#45000
b100 1
b1100011 (
b1100011 +
1%
#50000
b100 *
0%
#55000
b101 1
b1101 (
b1101 +
1%
#60000
b101 *
0%
#65000
b110 1
b10001101 (
b10001101 +
1%
#70000
b110 *
0%
#75000
1"
1,
b111 1
b1100101 (
b1100101 +
1%
#80000
b111 *
0%
#85000
b10010 (
b10010 +
1%
#90000
1&
0)
b0 *
0%
#95000
0"
0,
b1 0
bx !
bx /
1%
#100000
b1 *
0%
#105000
b10 0
b100100 !
b100100 /
1%
#110000
b10 *
0%
#115000
b11 0
b10000001 !
b10000001 /
1%
#120000
b11 *
0%
#125000
b100 0
b1001 !
b1001 /
1%
#130000
b100 *
0%
#135000
b101 0
b1100011 !
b1100011 /
1%
#140000
b101 *
0%
#145000
b110 0
b1101 !
b1101 /
1%
#150000
b110 *
0%
#155000
1#
1-
b111 0
b10001101 !
b10001101 /
1%
#160000
b111 *
0%
#165000
1%
#170000
b1000 *
0%
