CIDI-Modulos/VHDL/Task-5/C5_design.vhd
-- TASK E-105 (VHDL)
LIBRARY IEEE;
    USE IEEE.std_logic_1164.ALL;
    USE IEEE.STD_LOGIC_UNSIGNED.ALL;
    USE IEEE.numeric_std.ALL;

ENTITY vhdl_types IS
    PORT(
        clk                     : IN std_logic;
        rst                     : IN std_logic;
        signal_cnt              : OUT std_logic_vector(2 DOWNTO 0) := (OTHERS => '0')
    );
END ENTITY vhdl_types;

-- Testar configurações alternativas
ARCHITECTURE behavioural OF vhdl_types IS
    SIGNAL signal_counter       : std_logic_vector(2 DOWNTO 0);
    -- SIGNAL signal_counter    : signed(2 DOWNTO 0);
    -- SIGNAL signal_counter    : unsigned(2 DOWNTO 0);
    -- SiIGNAL signal_counter   : integer RANGE -4 TO 3;
    -- SIGNAL signal_counter    : natural RANGE 0 TO 7;

BEGIN

    PROCESS (clk, rst) BEGIN
        IF rst='1' THEN 
            signal_counter <= "000";
            --signal_counter <= 0;
        ELSIF rising_edge(clk) THEN
            signal_counter <= signal_counter + 1;
        END IF;
    END PROCESS;

    -- atribuição para a saída
    signal_cnt <= signal_counter;
    -- signal_cnt <= std_logic_vector(signal_counter);
    -- signal_cnt <= std_logic_vector(to_signed(signal_counter, 3));
    -- signal_cnt <= std_logic_vector(to_unsigned(signal_counter, 3));
END ARCHITECTURE;

CIDI-Modulos/VHDL/Task-5/C5_testbench.vhd
-- TASK E-105 (VHDL)
LIBRARY IEEE;
    USE IEEE.std_logic_1164.ALL;

ENTITY testbench_vhdl_types IS
END ENTITY testbench_vhdl_types;

ARCHITECTURE stimulus OF testbench_vhdl_types IS
    COMPONENT vhdl_types IS
        PORT(
            clk                     : IN std_logic;
            rst                     : IN std_logic;
            signal_cnt              : OUT std_logic_vector(2 DOWNTO 0)
        );
    END COMPONENT;

    SIGNAL clk, rst                 : std_logic := '1'; -- Default 
    SIGNAL sig_cnt                  : std_logic_vector(2 DOWNTO 0);
    CONSTANT PERIOD                 : time := 10 ns;
BEGIN

    -- clock generation
    PROCESS
    BEGIN
        WAIT FOR PERIOD/2;
        clk <= NOT clk;
    END PROCESS;

    PROCESS BEGIN
        WAIT FOR PERIOD/2;
        rst <= '0';
        WAIT;
    END PROCESS;

    sigvsvar : vhdl_types
        PORT MAP (
            clk                 => clk,
            rst                 => rst,
            signal_cnt          => sig_cnt
        );

END ARCHITECTURE;

CIDI-Modulos/VHDL/Task-5/waves/testbench_vhdl_types.vcd
$date
  Fri Dec 12 21:47:31 2025
$end
$version
  GHDL v0
$end
$timescale
  1 fs
$end
$scope module standard $end
$upscope $end
$scope module textio $end
$upscope $end
$scope module std_logic_1164 $end
$upscope $end
$scope module std_logic_arith $end
$upscope $end
$scope module std_logic_unsigned $end
$upscope $end
$scope module numeric_std $end
$upscope $end
$scope module testbench_vhdl_types $end
$var reg 1 ! clk $end
$var reg 1 " rst $end
$var reg 3 # sig_cnt[2:0] $end
$scope module sigvsvar $end
$var reg 1 $ clk $end
$var reg 1 % rst $end
$var reg 3 & signal_cnt[2:0] $end
$var reg 3 ' signal_counter[2:0] $end
$upscope $end
$upscope $end
$enddefinitions $end
#0
1!
1"
b000 #
1$
1%
b000 &
b000 '
#5000000
0!
0"
0$
0%
#10000000
1!
b001 #
1$
b001 &
b001 '
#15000000
0!
0$
#20000000
1!
b010 #
1$
b010 &
b010 '
#25000000
0!
0$
#30000000
1!
b011 #
1$
b011 &
b011 '
#35000000
0!
0$
#40000000
1!
b100 #
1$
b100 &
b100 '
#45000000
0!
0$
#50000000
1!
b101 #
1$
b101 &
b101 '
#55000000
0!
0$
#60000000
1!
b110 #
1$
b110 &
b110 '
#65000000
0!
0$
#70000000
1!
b111 #
1$
b111 &
b111 '
#75000000
0!
0$
#80000000
1!
b000 #
1$
b000 &
b000 '
#85000000
0!
0$
#90000000
1!
b001 #
1$
b001 &
b001 '
#95000000
0!
0$
#100000000
1!
b010 #
1$
b010 &
b010 '
#105000000
0!
0$
#110000000
1!
b011 #
1$
b011 &
b011 '
#115000000
0!
0$
#120000000
1!
b100 #
1$
b100 &
b100 '
#125000000
0!
0$
#130000000
1!
b101 #
1$
b101 &
b101 '
#135000000
0!
0$
#140000000
1!
b110 #
1$
b110 &
b110 '
#145000000
0!
0$
#150000000
1!
b111 #
1$
b111 &
b111 '
