CIDI-Modulos/SD132-CIRC-DIGITAIS-II/SD132-Task-6/Complementary-Task/mealy_pass.v
/*
Program: CI Digital T2/2025
Class: Introdução à Verilog  
Class-ID: SD122
Advisor: Felipe Rocha 
Advisor-Contact: felipef.rocha@inatel.br
Institute: INATEL - Santa Rita do Sapucaí / MG  
Development: André Bezerra 
Student-Contact: andrefrbezerra@gmail.com
Task-ID: A-106
Type: Laboratory
Data: november, 25 2025
*/

`timescale 1 ns / 1 ps;

module mealy_pass( // #(parameter PASS = 3'b101)(
    input 	clk,
    input 	rst_n,
    input 	x,
    output wire z // Mealy 
);

    // Definição dos estados
    localparam [1:0] S0 = 2'b00;
    localparam [1:0] S1 = 2'b01;
    localparam [1:0] S2 = 2'b10;

    reg [1:0] estado_atual, proximo_estado;

    // Lógica de transição de estados (sequencial)
    always @(posedge clk or negedge rst_n) begin
        if (!rst_n)
            estado_atual <= S0;
        else
            estado_atual <= proximo_estado;
    end

    // Lógica do próximo estado (combinacional)
    always @(*) begin
        case (estado_atual)
		// Check pass;
		S0: proximo_estado = (x == 1'b1) ? S1 : S0;
		S1: proximo_estado = (x == 1'b0) ? S2 : S1;
		S2: proximo_estado = (x == 1'b1) ? S1 : S0;
            	default: proximo_estado = S0;
        endcase
    end

	// Lógica de saída (característica de Mealy)
	assign z = (estado_atual == S2) && (x==1'b1);

endmodule

CIDI-Modulos/SD132-CIRC-DIGITAIS-II/SD132-Task-6/Complementary-Task/moore_pass.v
/*
Program: CI Digital T2/2025
Class: Introdução à Verilog  
Class-ID: SD122
Advisor: Felipe Rocha 
Advisor-Contact: felipef.rocha@inatel.br
Institute: INATEL - Santa Rita do Sapucaí / MG  
Development: André Bezerra 
Student-Contact: andrefrbezerra@gmail.com
Task-ID: A-106
Type: Laboratory
Data: november, 25 2025
*/

`timescale 1 ns / 1 ps;

module moore_pass( // #(parameter PASS = 3'b101)(
    input 	clk,
    input 	rst_n,
    input 	x,
    output reg  z // Moore - Latch 
);

    // Definição dos estados
    localparam [1:0] S0 = 2'b00;
    localparam [1:0] S1 = 2'b01;
    localparam [1:0] S2 = 2'b10;
    localparam [1:0] S3 = 2'b11;

    reg [1:0] estado_atual, proximo_estado;

    // Lógica de transição de estados (sequencial)
    always @(posedge clk or negedge rst_n) begin
    
    	estado_atual <= (!rst_n) ? S0 : proximo_estado;
    
    end

    // Lógica do próximo estado (combinacional)
    always @(*) begin
        case (estado_atual)
			// Check pass;
			S0: proximo_estado = (x == 1'b1) ? S1 : S0;
			S1: proximo_estado = (x == 1'b0) ? S2 : S1;
			S2: proximo_estado = (x == 1'b1) ? S3 : S0;
			// Checa sobreposição (Analisar sequencia de ativação)
			S3: proximo_estado = (x == 1'b0) ? S2 : S1; // S1:S0
            default: proximo_estado = S0;
        endcase
    end

    // Lógica de saída (característica de Moore)
    always @(*) begin
        z <= (estado_atual == S3);  
    end

endmodule

CIDI-Modulos/SD132-CIRC-DIGITAIS-II/SD132-Task-6/Complementary-Task/analysis_tb.v
/*
Program: CI Digital T2/2025
Class: Introdução à Verilog  
Class-ID: SD122
Advisor: Felipe Rocha 
Advisor-Contact: felipef.rocha@inatel.br
Institute: INATEL - Santa Rita do Sapucaí / MG  
Development: André Bezerra 
Student-Contact: andrefrbezerra@gmail.com
Task-ID: A-206
Type: Testbench
Data: november, 25 2025
*/

`timescale 1 ns / 1 ps;

module analysis_tb;

    // Sinais do Testbench
    reg clk;
    reg rst_n;
    reg x;

    // Fios para conectar aos módulos
    wire z_moore;
    wire z_mealy;

    // Instanciação dos Módulos (DUT - Device Under Test)
    moore_pass DUT0 (
        .clk(clk), .rst_n(rst_n), .x(x),
        .z(z_moore)
    );

    mealy_pass DUT1 (
        .clk(clk), .rst_n(rst_n), .x(x),
        .z(z_mealy)
    );

	// Geração de Clock
	always #1 clk = ~clk; // Período de 10ns

    // Sequência de Teste
    initial begin
        // 1. Reset
        {rst_n, x, clk} = 3'b000;
        #5;
        
	rst_n = 1'b1;

        // Enviar sequência de teste: 
	// sequence = 16b'0000000010101101
	// always @(posedge clk) x <= sequence[i]; i = i + 1'b1; 
        @(posedge clk) x <= 1'b0; 
        @(posedge clk) x <= 1'b1; 
        @(posedge clk) x <= 1'b1; 
        @(posedge clk) x <= 1'b0;
        @(posedge clk) x <= 1'b1; 
        @(posedge clk) x <= 1'b0;
        @(posedge clk) x <= 1'b1;
        @(posedge clk) x <= 1'b1;
        @(posedge clk) x <= 1'b0;
        @(posedge clk) x <= 1'b1;
        @(posedge clk) x <= 1'b0;
        @(posedge clk) x <= 1'b0; // Stopping here
        @(posedge clk) x <= 1'b0;
        @(posedge clk) x <= 1'b1;
        @(posedge clk) x <= 1'b0;
        @(posedge clk) x <= 1'b1;
        @(posedge clk) x <= 1'b0;
        @(posedge clk) x <= 1'b1;
        @(posedge clk) x <= 1'b0;

        // Finaliza a simulação
        @(posedge clk);
        
	#10;
        $finish;
    end

	// Monitorar os sinais para visualização
	initial begin
		
		// Specify the VCD file name
		$dumpfile("CIDI-SD132-A206-mome.vcd"); 
        	$dumpvars(0, analysis_tb);

		$display("|Time	|Reset	|Input	|Moore	 |Mealy	  |");
        	$monitor("|%0t	|%b	|%b	|st:%d z:%b|st:%d z:%b|",
            		$time, rst_n, x,
            		DUT0.estado_atual, z_moore,
        	    	DUT1.estado_atual, z_mealy
		);
	end

endmodule

CIDI-Modulos/SD132-CIRC-DIGITAIS-II/SD132-Task-6/Complementary-Task/CIDI-SD132-A206-mome.vcd
$date
	Tue Nov 25 20:04:41 2025
$end
$version
	Icarus Verilog
$end
$timescale
	1ps
$end
$scope module analysis_tb $end
$var wire 1 ! z_moore $end
$var wire 1 " z_mealy $end
$var reg 1 # clk $end
$var reg 1 $ rst_n $end
$var reg 1 % x $end
$scope module DUT0 $end
$var wire 1 # clk $end
$var wire 1 $ rst_n $end
$var wire 1 % x $end
$var parameter 2 & S0 $end
$var parameter 2 ' S1 $end
$var parameter 2 ( S2 $end
$var parameter 2 ) S3 $end
$var reg 2 * estado_atual [1:0] $end
$var reg 2 + proximo_estado [1:0] $end
$var reg 1 ! z $end
$upscope $end
$scope module DUT1 $end
$var wire 1 # clk $end
$var wire 1 $ rst_n $end
$var wire 1 % x $end
$var wire 1 " z $end
$var parameter 2 , S0 $end
$var parameter 2 - S1 $end
$var parameter 2 . S2 $end
$var reg 2 / estado_atual [1:0] $end
$var reg 2 0 proximo_estado [1:0] $end
$upscope $end
$upscope $end
$enddefinitions $end
$comment Show the parameter values. $end
$dumpall
b10 .
b1 -
b0 ,
b11 )
b10 (
b1 '
b0 &
$end
#0
$dumpvars
b0 0
b0 /
b0 +
b0 *
0%
0$
0#
0"
0!
$end
#1000
1#
#2000
0#
#3000
1#
#4000
0#
#5000
1#
1$
#6000
0#
#7000
b1 +
b1 0
1%
1#
#8000
0#
#9000
b1 /
b1 *
1#
#10000
0#
#11000
b10 +
b10 0
0%
1#
#12000
0#
#13000
1"
b11 +
b1 0
b10 /
b10 *
1%
1#
#14000
0#
#15000
1!
0"
b10 +
b10 0
b11 *
b1 /
0%
1#
#16000
0#
#17000
0!
1"
b11 +
b1 0
b10 /
b10 *
1%
1#
#18000
0#
#19000
1!
b1 +
0"
b11 *
b1 /
1#
#20000
0#
#21000
0!
b10 +
b10 0
b1 *
0%
1#
#22000
0#
#23000
1"
b11 +
b1 0
b10 *
b10 /
1%
1#
#24000
0#
#25000
1!
0"
b10 +
b10 0
b1 /
b11 *
0%
1#
#26000
0#
#27000
0!
b0 +
b0 0
b10 *
b10 /
1#
#28000
0#
#29000
b0 /
b0 *
1#
#30000
0#
#31000
b1 +
b1 0
1%
1#
#32000
0#
#33000
b10 +
b10 0
b1 /
b1 *
0%
1#
#34000
0#
#35000
1"
b11 +
b1 0
b10 *
b10 /
1%
1#
#36000
0#
#37000
1!
0"
b10 +
b10 0
b1 /
b11 *
0%
1#
#38000
0#
#39000
0!
1"
b11 +
b1 0
b10 *
b10 /
1%
1#
#40000
0#
#41000
1!
0"
b10 +
b10 0
b1 /
b11 *
0%
1#
#42000
0#
#43000
0!
b0 +
b0 0
b10 *
b10 /
1#
#44000
0#
#45000
b0 /
b0 *
1#
