CIDI-Modulos/SD112-INTRO-VERILOG/SD112-Task-10/circuit_test3.v
/*
Program: CI Digital T2/2025
Class: Introdução à Verilog  
Class-ID: SD112
Advisor: Felipe Rocha 
Advisor-Contact: felipef.rocha@inatel.br
Institute: INATEL - Santa Rita do Sapucaí / MG  
Development: André Bezerra 
Student-Contact: andrefrbezerra@gmail.com
Task-ID: A-010
Type: Laboratory
Data: octuber, 17 2025
*/

`timescale 1 ns / 1 ps;

// Atividade A-010-3

module circuit_test3 ( // Definir função
	input a, b, c, d,
	output s 
);
	
	wire n_a, n_b, n_c, n_d, and_1, or_1, nor_1, nor_2;

 	not n1 (n_a, a);
 	not n2 (n_b, b);
 	not n3 (n_c, c);
 	not n4 (n_d, d);
 	
	// Reavaliar o circuito; 
 	and a1 (and_1, n_a, b);
 	or  o1 (or_1, c, n_d);
 	nor nr1 (nor_1, n_b, d);
 	
 	nor nr2 (nor_2, and_1, or_1);

 	nand nd1 (s, nor_2, nor_1);
 	
 endmodule

CIDI-Modulos/SD112-INTRO-VERILOG/SD112-Task-10/circuit_test3_tb.v
/*
Program: CI Digital T2/2025
Class: Introdução à Verilog  
Class-ID: SD112
Advisor: Felipe Rocha 
Advisor-Contact: felipef.rocha@inatel.br
Institute: INATEL - Santa Rita do Sapucaí / MG  
Development: André Bezerra 
Student-Contact: andrefrbezerra@gmail.com
Task-ID: A-010
Type: Testbench
Data: octuber, 17 2025
*/

`timescale 1 ns / 1 ps;
  
module circuit_test3_tb;

	localparam DELAY = 10; // , SAMPLES = 16;  
	reg a, b,c, d;
	wire s;

	circuit_test3 UUT (
		.a(a), .b(b), .c(c), .d(d),
		.s(s)
	);

	initial begin
	
		// Specify the VCD file name
		$dumpfile("CIDI-SD112-A010-4.vcd"); 
		$dumpvars(0, circuit_test3_tb); 
		
		// for(i = 0; i < SAMPLES-1; i = i + 1) begin 
		// 		{a,b,c,d} = 4'di; #DELAY;
		// ... end
		
		{a,b,c,d} = 4'b0001;
		#DELAY; 
		
		{a,b,c,d} = 4'b0010;
		#DELAY; 
		
		{a,b,c,d} = 4'b0100;
		#DELAY; 
		
		{a,b,c,d} = 4'b0101;
		#DELAY; 
		
		{a,b,c,d} = 4'b0110;
		#DELAY; 
		
		{a,b,c,d} = 4'b0111;
		#DELAY; 
		
		{a,b,c,d} = 4'b1000;
		#DELAY;
		
		{a,b,c,d} = 4'b1001;
		#DELAY; 
		
		{a,b,c,d} = 4'b1010;
		#DELAY; 
		
		{a,b,c,d} = 4'b1100;
		#DELAY; 
		
		{a,b,c,d} = 4'b1101;
		#DELAY; 
		
		{a,b,c,d} = 4'b1110;
		#DELAY; 
		
		{a,b,c,d} = 4'b1111;
		#DELAY; 
		
		$finish;
	end
                
endmodule

CIDI-Modulos/SD112-INTRO-VERILOG/SD112-Task-10/CIDI-SD112-A010-4-ex3.vcd
$date
	Tue Nov 18 23:30:13 2025
$end
$version
	Icarus Verilog
$end
$timescale
	1ps
$end
$scope module circuit_test3_tb $end
$var wire 1 ! s $end
$var parameter 32 " DELAY $end
$var reg 1 # a $end
$var reg 1 $ b $end
$var reg 1 % c $end
$var reg 1 & d $end
$scope module UUT $end
$var wire 1 # a $end
$var wire 1 ' and_1 $end
$var wire 1 $ b $end
$var wire 1 % c $end
$var wire 1 & d $end
$var wire 1 ( n_a $end
$var wire 1 ) n_b $end
$var wire 1 * n_c $end
$var wire 1 + n_d $end
$var wire 1 , nor_1 $end
$var wire 1 - nor_2 $end
$var wire 1 . or_1 $end
$var wire 1 ! s $end
$upscope $end
$upscope $end
$enddefinitions $end
$comment Show the parameter values. $end
$dumpall
b1010 "
$end
#0
$dumpvars
0.
1-
0,
0+
1*
1)
1(
0'
1&
0%
0$
0#
1!
$end
#10000
0-
0*
1.
1+
1%
0&
#20000
1,
0)
1'
1*
1$
0%
#30000
0.
0+
0,
1&
#40000
0*
1.
1+
1,
1%
0&
#50000
0+
0,
1&
#60000
0(
1)
0'
1*
1+
0,
1#
0$
0%
0&
#70000
1-
0.
0+
1&
#80000
0-
0*
1.
1+
1%
0&
#90000
1,
0)
1*
1$
0%
#100000
1-
0.
0+
0,
1&
#110000
0-
1!
0*
1.
1+
1,
1%
0&
#120000
0+
0,
1&
