CIDI-Modulos/SD122-CIRC-DIGITAIS-I/SD122-Task-2/A102-1/task-1/conversor.v
/*
Program: CI Digital T2/2025
Class: Introdução à Verilog  
Class-ID: SD122
Advisor: Felipe Rocha 
Advisor-Contact: felipef.rocha@inatel.br
Institute: INATEL - Santa Rita do Sapucaí / MG  
Development: André Bezerra 
Student-Contact: andrefrbezerra@gmail.com
Task-ID: A-102-1
Type: Laboratory
Data: november, 5 2025
*/

`timescale 1 ns / 1 ps;

module S_D(
	input H,G,
	output D
);
	assign D = H & G;

endmodule

module S_C(
	input H,G,E,
	output C
);
	assign C = (!H & G & E) | (H & !G); // (E & !H & G ) | (H & !G);

endmodule

module S_B(
	input H,G,F,E,
	output B
);
	assign B = (!H & G & !E) | (!G & F) | (H & !G); 
	// (G & !H & !E) | (!G & (F | H))

endmodule

module S_A(
	input H,G,F,E,
	output A
);
	assign A = (!H & !G & !F & E) | (!H & G & !E) | (G & F) | (H & G & E) | (H & F);
	// !H & ((!F & !G & E) | (G & !E)) | (G & F) | (H & (G & E | F));
endmodule

module top(
    input  H,G,F,E,
    output D,C,B,A
);
    S_D sd(.H(H), .G(G), .D(D)		    );
    S_C sc(.H(H), .G(G), .E(E), .C(C)	    );
    S_B sb(.H(H), .G(G), .F(F), .E(E), .B(B));
    S_A sa(.H(H), .G(G), .F(F), .E(E), .A(A));

endmodule

CIDI-Modulos/SD122-CIRC-DIGITAIS-I/SD122-Task-2/A102-1/task-1/conversor_tb.v
/*
Program: CI Digital T2/2025
Class: Introdução à Verilog  
Class-ID: SD122
Advisor: Felipe Rocha 
Advisor-Contact: felipef.rocha@inatel.br
Institute: INATEL - Santa Rita do Sapucaí / MG  
Development: André Bezerra 
Student-Contact: andrefrbezerra@gmail.com
Task-ID: A-102-1
Type: Testbench
Data: november, 5 2025
*/

`timescale 1 ns / 1 ps;

module conversor_tb();

	localparam DELAY = 10; 
	wire A, B, C, D;
	reg  E, F, G, H;

	top CONV_TB(
        	.H(H), .G(G), .F(F), .E(E), 
        	.D(D), .C(C), .B(B), .A(A)
	);

	initial begin

		$dumpfile("CIDI-SD122-A102-1-1.vcd");
		$dumpvars(0, conversor_tb);

		$display("|A B C D	|E F G H	|");
		
		$monitor("|%b %b %b %b	|%b %b %b %b	|", A, B, C, D, E, F, G, H);
    
		{H,G,F,E} = 4'b0000; #DELAY;
		{H,G,F,E} = 4'b0001; #DELAY;
		{H,G,F,E} = 4'b0011; #DELAY;
		{H,G,F,E} = 4'b0100; #DELAY;
		{H,G,F,E} = 4'b0101; #DELAY;
		{H,G,F,E} = 4'b0111; #DELAY;
		{H,G,F,E} = 4'b1001; #DELAY;
		{H,G,F,E} = 4'b1011; #DELAY;
		{H,G,F,E} = 4'b1100; #DELAY;
		{H,G,F,E} = 4'b1101; #DELAY;

        	$finish;
	end

endmodule

CIDI-Modulos/SD122-CIRC-DIGITAIS-I/SD122-Task-2/A102-1/task-1/CIDI-SD122-A102-1-1.vcd
$date
	Mon Nov 24 04:17:49 2025
$end
$version
	Icarus Verilog
$end
$timescale
	1ps
$end
$scope module conversor_tb $end
$var wire 1 ! D $end
$var wire 1 " C $end
$var wire 1 # B $end
$var wire 1 $ A $end
$var parameter 32 % DELAY $end
$var reg 1 & E $end
$var reg 1 ' F $end
$var reg 1 ( G $end
$var reg 1 ) H $end
$scope module CONV_TB $end
$var wire 1 & E $end
$var wire 1 ' F $end
$var wire 1 ( G $end
$var wire 1 ) H $end
$var wire 1 ! D $end
$var wire 1 " C $end
$var wire 1 # B $end
$var wire 1 $ A $end
$scope module sa $end
$var wire 1 $ A $end
$var wire 1 & E $end
$var wire 1 ' F $end
$var wire 1 ( G $end
$var wire 1 ) H $end
$upscope $end
$scope module sb $end
$var wire 1 # B $end
$var wire 1 & E $end
$var wire 1 ' F $end
$var wire 1 ( G $end
$var wire 1 ) H $end
$upscope $end
$scope module sc $end
$var wire 1 " C $end
$var wire 1 & E $end
$var wire 1 ( G $end
$var wire 1 ) H $end
$upscope $end
$scope module sd $end
$var wire 1 ! D $end
$var wire 1 ( G $end
$var wire 1 ) H $end
$upscope $end
$upscope $end
$upscope $end
$enddefinitions $end
$comment Show the parameter values. $end
$dumpall
b1010 %
$end
#0
$dumpvars
0)
0(
0'
0&
0$
0#
0"
0!
$end
#10000
1$
1&
#20000
0$
1#
1'
#30000
1$
1#
1(
0'
0&
#40000
0$
0#
1"
1&
#50000
1$
1'
#60000
0$
1#
1)
0(
0'
#70000
1$
1'
#80000
0#
0"
0$
1!
1(
0'
0&
#90000
1$
1&
