CIDI-Modulos/SD122-CIRC-DIGITAIS-I/SD122-Task-6/ex_02/demux_1x8.v
module demux_1x2(
    input din,
    input sel,
    output y0, y1
);
    assign y0 = din & ~sel;
    assign y1 = din &  sel;

endmodule

module demux_1x8(
    input d,
    input [2:0] sel,
    output [7:0] y
);
    wire [1:0] m;
    wire [3:0] n;

    // Nível 1: primeiro demux
    demux_1x2 d0 (.din(d), .sel(sel[2]), .y0(m[0]), .y1(m[1]));
    
    // Nível 2: cada saída do nível 1 vai para outro demux
    demux_1x2 d1 (.din(m[0]), .sel(sel[1]), .y0(n[0]), .y1(n[1]));
    demux_1x2 d2 (.din(m[0]), .sel(sel[1]), .y0(n[2]), .y1(n[3]));  

    // Nível 3: cada saída do nível 2 vai para outro demux
    demux_1x2 d3 (.din(n[0]), .sel(sel[0]), .y0(y[0]), .y1(y[1]));
    demux_1x2 d4 (.din(n[1]), .sel(sel[0]), .y0(y[2]), .y1(y[3]));
    demux_1x2 d5 (.din(n[2]), .sel(sel[0]), .y0(y[4]), .y1(y[5]));
    demux_1x2 d6 (.din(n[3]), .sel(sel[0]), .y0(y[6]), .y1(y[7]));

endmodule

CIDI-Modulos/SD122-CIRC-DIGITAIS-I/SD122-Task-6/ex_02/demux_1x8_tb.v
`timescale 1ns/1ps
`include "demux_1x8.v"

module demux_1x8_tb;
    reg din;
    reg [2:0] sel;
    wire [7:0] y;

    demux_1x8 uut(.d(din), .sel(sel), .y(y));

    initial begin
        $dumpfile("demux_1x8_tb.vcd");
        $dumpvars(0, demux_1x8_tb);

        din = 1'b1;
        
        sel = 3'b000; #5; 
        sel = 3'b001; #5; 
        sel = 3'b010; #5; 
        sel = 3'b011; #5; 
        sel = 3'b100; #5; 
        sel = 3'b101; #5; 
        sel = 3'b110; #5; 
        sel = 3'b111; #5; 

        $finish;
    end
endmodule

CIDI-Modulos/SD122-CIRC-DIGITAIS-I/SD122-Task-6/ex_02/demux_1x8_tb.vcd
$date
	Mon Nov 03 09:41:43 2025
$end
$version
	Icarus Verilog
$end
$timescale
	1ps
$end
$scope module demux_1x8_tb $end
$var wire 8 ! y [7:0] $end
$var reg 1 " din $end
$var reg 3 # sel [2:0] $end
$scope module uut $end
$var wire 1 " d $end
$var wire 3 $ sel [2:0] $end
$var wire 8 % y [7:0] $end
$var wire 4 & n [3:0] $end
$var wire 2 ' m [1:0] $end
$scope module d0 $end
$var wire 1 " din $end
$var wire 1 ( sel $end
$var wire 1 ) y0 $end
$var wire 1 * y1 $end
$upscope $end
$scope module d1 $end
$var wire 1 + din $end
$var wire 1 , sel $end
$var wire 1 - y0 $end
$var wire 1 . y1 $end
$upscope $end
$scope module d2 $end
$var wire 1 / din $end
$var wire 1 0 sel $end
$var wire 1 1 y0 $end
$var wire 1 2 y1 $end
$upscope $end
$scope module d3 $end
$var wire 1 3 din $end
$var wire 1 4 sel $end
$var wire 1 5 y0 $end
$var wire 1 6 y1 $end
$upscope $end
$scope module d4 $end
$var wire 1 7 din $end
$var wire 1 8 sel $end
$var wire 1 9 y0 $end
$var wire 1 : y1 $end
$upscope $end
$scope module d5 $end
$var wire 1 ; din $end
$var wire 1 < sel $end
$var wire 1 = y0 $end
$var wire 1 > y1 $end
$upscope $end
$scope module d6 $end
$var wire 1 ? din $end
$var wire 1 @ sel $end
$var wire 1 A y0 $end
$var wire 1 B y1 $end
$upscope $end
$upscope $end
$upscope $end
$enddefinitions $end
$comment Show the parameter values. $end
$dumpall
$end
#0
$dumpvars
0B
0A
0@
0?
0>
1=
0<
1;
0:
09
08
07
06
15
04
13
02
11
00
1/
0.
1-
0,
1+
0*
1)
0(
b1 '
b101 &
b10001 %
b0 $
b0 #
1"
b10001 !
$end
#5000
05
0=
16
b100010 !
b100010 %
1>
14
18
1<
1@
b1 #
b1 $
#10000
03
19
0;
1A
0-
17
01
1?
05
0=
1.
b1010 &
12
06
b1000100 !
b1000100 %
0>
1,
10
04
08
0<
0@
b10 #
b10 $
#15000
09
0A
1:
b10001000 !
b10001000 %
1B
14
18
1<
1@
b11 #
b11 $
#20000
05
0=
0+
0/
03
0;
0)
0-
07
01
0?
09
0A
b10 '
1*
0.
b0 &
02
0:
b0 !
b0 %
0B
1(
0,
00
04
08
0<
0@
b100 #
b100 $
#25000
14
18
1<
1@
b101 #
b101 $
#30000
1,
10
04
08
0<
0@
b110 #
b110 $
#35000
14
18
1<
1@
b111 #
b111 $
