CIDI-Modulos/SD122-CIRC-DIGITAIS-I/SD122-Task-14/fixed_point_adder.v
/*
Program: CI Digital 02/2025
Class: Introdução à Verilog  
Class-ID: D122
Advisor: Felipe Rocha 
Advisor-Contact: felipef.rocha@inatel.br
Institute: INATEL - Santa Rita do Sapucaí / MG  
Development: André Bezerra 
Student-Contact: andrefrbezerra@gmail.com
Task-ID: A-114
Type: Laboratory
Data: november, 13 2025
*/

`timescale 1 ns / 1 ps;

module  fixed_point_adder #(parameter Q = 4, N = 2*Q) (
    input [N-1:0] a,
    input [N-1:0] b,
    output [N-1:0] c
);

	reg [N-1:0] res;
	// Aplicar um valor de controle para res.
	
	assign c = res;

	always @(a,b) begin
		
		// Análise condicional da estrutura 
		// valores com sinal 
		
		// both negative or both positive
		if(a[N-1] == b[N-1]) begin						//	Since they have the same sign, absolute magnitude increase<Left>
			res[N-2:0] = a[N-2:0] + b[N-2:0]; //
			res[N-1] = a[N-1]; 
			// and set the sign appropriately...  Doesn't matter which one we use
			// they both have the same sign 
			// Do the sign last, on the off-chance there was an overflow...  
		end
		
		// Not doing any error checking on this...
		// one of them is negative...
		else if( a[N-1] == 0 && b[N-1] == 1) begin	
			// subtract a-b
			if( a[N-2:0] > b[N-2:0] ) begin				
				// if a is greater than b,
				res[N-2:0] = a[N-2:0] - b[N-2:0];			
				// then just subtract b from a
				res[N-1] = 0;
			// and manually set the sign to positive
			end
		else begin
			// if a is less than b,
			res[N-2:0] = b[N-2:0] - a[N-2:0];			
			// we'll actually subtract a from b to avoid a 2's complement answer
			if (res[N-2:0] == 0)
				res[N-1] = 0;
				// I don't like negative zero....
			else
				res[N-1] = 1;
				// and manually set the sign to negative
			end
		end
		else begin
			// subtract b-a (a negative, b positive)
			if( a[N-2:0] > b[N-2:0] ) begin
				// if a is greater than b,
				res[N-2:0] = a[N-2:0] - b[N-2:0];
				// we'll actually subtract b from a to avoid a 2's complement answer
				
				// Alternativa 
				if (res[N-2:0] == 0)
					res[N-1] = 0;
					// I don't like negative zero....
				else
					res[N-1] = 1;
				// and manually set the sign to negative
			end
			
			else begin
				// if a is less than b,
				res[N-2:0] = b[N-2:0] - a[N-2:0];			
				// then just subtract a from b
				res[N-1] = 0;
				// and manually set the sign to positive
			end
		end
	end
endmodule

CIDI-Modulos/SD122-CIRC-DIGITAIS-I/SD122-Task-14/fixed_point_adder_tb.v
/*
Program: CI Digital T2/2025
Class: Introdução à Verilog  
Class-ID: SD122
Advisor: Felipe Rocha 
Advisor-Contact: felipef.rocha@inatel.br
Institute: INATEL - Santa Rita do Sapucaí / MG  
Development: André Bezerra 
Student-Contact: andrefrbezerra@gmail.com
Task-ID: A-114
Type: Testbench
Data: november, 13 2025
*/

`timescale 1 ns / 1 ps;

module fixed_point_adder_tb;

	// parâmetros
	localparam DELAY = 10, SAMPLES = 10;
	localparam N = 8, M = 4;
	
	reg [N-1:0] a;
	reg [N-1:0] b;

	// Outputs
	wire [N-1:0] c;
	integer i; 

	// Instantiate the Unit Under Test (UUT)
	fixed_point_adder #(M+3,N) uut (
		.a(a), 
		.b(b), 
		.c(c)
	);

	//	These are to monitor the values...
	wire	[N-2:0]	c_out;
	wire	[N-2:0]	a_in;
	wire	[N-2:0]	b_in;
	wire	a_sign;
	wire	b_sign;
	wire	c_sign;
	
	
	assign	a_in = a[N-2:0];
	assign	b_in = b[N-2:0];
	assign	c_out = c[N-2:0];
	assign	a_sign = a[N-1];
	assign	b_sign = b[N-1];
	assign	c_sign = c[N-1];
	
	
	initial begin
		
		// Specify the VCD file name
		$dumpfile("CID-SD122-A114-fixed-point-adder.vcd"); 
        	$dumpvars(0, fixed_point_adder_tb); 
		
		// Atualizar vizualização dos dados
		$display("|i 	|a	|b	|c	|");
		$monitor("|%d	|%d	|%d	|%d	|", i, a, b, c);

		// Initialize Inputs
		a[N-2 : 0] = 0; // Zerar a referência
		a[N-1] = 0; 

		b[N-1] = 1'b0;
		b[N-2:0] = 3'b001;

		// Wait 100 ns for global reset to finish
        
		// Add stimulus here
		 for (i = 0; i < SAMPLES; i = i + 1) begin
			
			#DELAY; 
			a = a + 5;			//	why not?
			a[N-1] = 0;					//	a is negative...
			b[N-1] = 1;
			
			
			if (a[N-2 : 0] > 2.1E4) begin // Definir parameter
			// input will always be "positive"
				
				a = 0; // {N{0}};
				b[N-1] = 1;
				
				// b is negative... 
				// [ ] Corrigir valor de referência
				// Inverter o sistema o valor de b
				b[N-2 : 0] = ~b[N-2 : 0] + 1; // para 2.1E9 -> 3779351;
			end
		end
		
		#DELAY; 
		$finish; 
	end
	 
endmodule

CIDI-Modulos/SD122-CIRC-DIGITAIS-I/SD122-Task-14/CID-SD122-A114-fixed-point-adder.vcd
$date
	Tue Nov 18 19:44:51 2025
$end
$version
	Icarus Verilog
$end
$timescale
	1ps
$end
$scope module fixed_point_adder_tb $end
$var wire 1 ! c_sign $end
$var wire 7 " c_out [6:0] $end
$var wire 8 # c [7:0] $end
$var wire 1 $ b_sign $end
$var wire 7 % b_in [6:0] $end
$var wire 1 & a_sign $end
$var wire 7 ' a_in [6:0] $end
$var parameter 32 ( DELAY $end
$var parameter 32 ) M $end
$var parameter 32 * N $end
$var parameter 32 + SAMPLES $end
$var reg 8 , a [7:0] $end
$var reg 8 - b [7:0] $end
$var integer 32 . i [31:0] $end
$scope module uut $end
$var wire 8 / a [7:0] $end
$var wire 8 0 b [7:0] $end
$var wire 8 1 c [7:0] $end
$var parameter 32 2 N $end
$var parameter 33 3 Q $end
$var reg 8 4 res [7:0] $end
$upscope $end
$upscope $end
$enddefinitions $end
$comment Show the parameter values. $end
$dumpall
b111 3
b1000 2
b1010 +
b1000 *
b100 )
b1010 (
$end
#0
$dumpvars
b1 4
b1 1
b1 0
b0 /
b0 .
b1 -
b0 ,
b0 '
0&
b1 %
0$
b1 #
b1 "
0!
$end
#10000
b100 "
1$
b101 '
b100 #
b100 1
b100 4
b1 .
b10000001 -
b10000001 0
b101 ,
b101 /
#20000
b1001 "
b1010 '
b1001 #
b1001 1
b1001 4
b10 .
b1010 ,
b1010 /
#30000
b1110 "
b1111 '
b1110 #
b1110 1
b1110 4
b11 .
b1111 ,
b1111 /
#40000
b10011 "
b10100 '
b10011 #
b10011 1
b10011 4
b100 .
b10100 ,
b10100 /
#50000
b11000 "
b11001 '
b11000 #
b11000 1
b11000 4
b101 .
b11001 ,
b11001 /
#60000
b11101 "
b11110 '
b11101 #
b11101 1
b11101 4
b110 .
b11110 ,
b11110 /
#70000
b100010 "
b100011 '
b100010 #
b100010 1
b100010 4
b111 .
b100011 ,
b100011 /
#80000
b100111 "
b101000 '
b100111 #
b100111 1
b100111 4
b1000 .
b101000 ,
b101000 /
#90000
b101100 "
b101101 '
b101100 #
b101100 1
b101100 4
b1001 .
b101101 ,
b101101 /
#100000
b110001 "
b110010 '
b110001 #
b110001 1
b110001 4
b1010 .
b110010 ,
b110010 /
