CIDI-Modulos/SD122-CIRC-DIGITAIS-I/SD122-Task-3/task-1/prdd_coder.v
/*
Program: CI Digital T2/2025
Class: Introdução à Verilog  
Class-ID: SD122
Advisor: Felipe Rocha 
Advisor-Contact: felipef.rocha@inatel.br
Institute: INATEL - Santa Rita do Sapucaí / MG  
Development: André Bezerra 
Student-Contact: andrefrbezerra@gmail.com
Task-ID: A-103
Type: Laboratory
Data: octuber, 17 2025
*/

`timescale 1 ns / 1 ps;

module prdd_coder #(parameter N = 16, M = 4)(
    input wire [N-1 : 0] in,
    output reg [M-1 : 0] out
);
   always @(*) begin
        casex (in)
            16'b1xxxxxxxxxxxxxxx : out = 4'b1111;
            16'b01xxxxxxxxxxxxxx : out = 4'b1110;
            16'b001xxxxxxxxxxxxx : out = 4'b1101;
            16'b0001xxxxxxxxxxxx : out = 4'b1100;
            16'b00001xxxxxxxxxxx : out = 4'b1011;
            16'b000001xxxxxxxxxx : out = 4'b1010;
            16'b0000001xxxxxxxxx : out = 4'b1001;
            16'b00000001xxxxxxxx : out = 4'b1000;
            16'b000000001xxxxxxx : out = 4'b0111;
            16'b0000000001xxxxxx : out = 4'b0110;
            16'b00000000001xxxxx : out = 4'b0101;
            16'b000000000001xxxx : out = 4'b0100;
            16'b0000000000001xxx : out = 4'b0011;
            16'b00000000000001xx : out = 4'b0010;
            16'b000000000000001x : out = 4'b0001;
            16'b0000000000000001 : out = 4'b0000;
            default: out = 4'b0000;
        endcase
   end

endmodule

CIDI-Modulos/SD122-CIRC-DIGITAIS-I/SD122-Task-3/task-1/prdd_coder_tb.v
/*
Program: CI Digital T2/2025
Class: Introdução à Verilog  
Class-ID: SD122
Advisor: Felipe Rocha 
Advisor-Contact: felipef.rocha@inatel.br
Institute: INATEL - Santa Rita do Sapucaí / MG  
Development: André Bezerra 
Student-Contact: andrefrbezerra@gmail.com
Task-ID: A-103
Type: Testbench
Data: octuber, 17 2025
*/

`timescale 1 ns / 1 ps;

module prdd_coder_tb();

	localparam DELAY = 10, N = 16, M = 4; 
	reg  [N-1 : 0] in;
	wire [M-1 : 0] out;

	prdd_coder UUT (
		.in(in),
		.out(out)
	);

	initial begin
    
    		$dumpfile("CIDI-SD122-A103-1.vcd");
		$dumpvars(0, prdd_coder_tb);

		$display("|In			|Out	|");
		$monitor("|%b	|%b	|", in, out);
		
		// in = {WIDTH{1'b0}}; for () begin ... 
		// if (i == 0) in = in + 1'b1 else in << 1; // deslocar bit
		in = 16'b0000000000000000; #DELAY;
		in = 16'b1000000000000000; #DELAY;
		in = 16'b0100000000000000; #DELAY;
		in = 16'b0010000000000000; #DELAY;
		in = 16'b0001000000000000; #DELAY;
		in = 16'b0000100000000000; #DELAY;
		in = 16'b0000010000000000; #DELAY;
		in = 16'b0000001000000000; #DELAY;
		in = 16'b0000000100000000; #DELAY;
		in = 16'b0000000010000000; #DELAY;
		in = 16'b0000000001000000; #DELAY;
		in = 16'b0000000000100000; #DELAY;
		in = 16'b0000000000010000; #DELAY;
		in = 16'b0000000000001000; #DELAY;
		in = 16'b0000000000000100; #DELAY;
		in = 16'b0000000000000010; #DELAY;
		in = 16'b0000000000000001; #DELAY;
		$finish;
	end
    

endmodule

CIDI-Modulos/SD122-CIRC-DIGITAIS-I/SD122-Task-3/task-1/CIDI-SD122-A103-1.vcd
$date
	Wed Nov 26 15:36:09 2025
$end
$version
	Icarus Verilog
$end
$timescale
	1ps
$end
$scope module prdd_coder_tb $end
$var wire 4 ! out [3:0] $end
$var parameter 32 " DELAY $end
$var parameter 32 # M $end
$var parameter 32 $ N $end
$var reg 16 % in [15:0] $end
$scope module UUT $end
$var wire 16 & in [15:0] $end
$var parameter 32 ' M $end
$var parameter 32 ( N $end
$var reg 4 ) out [3:0] $end
$upscope $end
$upscope $end
$enddefinitions $end
$comment Show the parameter values. $end
$dumpall
b10000 (
b100 '
b10000 $
b100 #
b1010 "
$end
#0
$dumpvars
b0 )
b0 &
b0 %
b0 !
$end
#10000
b1111 !
b1111 )
b1000000000000000 %
b1000000000000000 &
#20000
b1110 !
b1110 )
b100000000000000 %
b100000000000000 &
#30000
b1101 !
b1101 )
b10000000000000 %
b10000000000000 &
#40000
b1100 !
b1100 )
b1000000000000 %
b1000000000000 &
#50000
b1011 !
b1011 )
b100000000000 %
b100000000000 &
#60000
b1010 !
b1010 )
b10000000000 %
b10000000000 &
#70000
b1001 !
b1001 )
b1000000000 %
b1000000000 &
#80000
b1000 !
b1000 )
b100000000 %
b100000000 &
#90000
b111 !
b111 )
b10000000 %
b10000000 &
#100000
b110 !
b110 )
b1000000 %
b1000000 &
#110000
b101 !
b101 )
b100000 %
b100000 &
#120000
b100 !
b100 )
b10000 %
b10000 &
#130000
b11 !
b11 )
b1000 %
b1000 &
#140000
b10 !
b10 )
b100 %
b100 &
#150000
b1 !
b1 )
b10 %
b10 &
#160000
b0 !
b0 )
b1 %
b1 &
