CIDI-Modulos/SD142-CIRC-DIGITAIS-III/A-306/MAC_complex.v
/*
Program: CI Digital T2/2025
Class: Circuito Digitais III 
Class-ID: SD142
Advisor: Felipe Rocha 
Advisor-Contact: felipef.rocha@inatel.br
Institute: INATEL - Santa Rita do Sapucaí / MG  
Development: André Bezerra 
Student-Contact: andrefrbezerra@gmail.com
Task-ID: A-306
Type: Laboratory
Data: febuary, 03 2026
*/
`timescale 1 ns / 1 ps

module MAC_complex #(
	parameter	WIDHT_IN = 8, 
				WIDHT_OUT = 32,	
				DEFAULT_RE = {WIDHT_OUT{1'b0}},	
				DEFAULT_IM = {WIDHT_OUT{1'b0}}
)(
    input 						clk, rst, en,
    input	[WIDHT_IN-1  : 0]	reA, reB, imA, imB,

    output	[WIDHT_OUT-1 : 0]	X, Y
);

    wire signed [WIDHT_IN*2-1 : 0]	product1_re,
									product2_re,
									product1_im,
									product2_im;

    wire signed [WIDHT_OUT-1 : 0] sum_re, 
    							  sum_im; 

    reg signed [WIDHT_OUT-1 : 0] accumulator_re,
    							 accumulator_im;

	// Parte Real
    assign product1_re = $signed(reA) * $signed(reB);
    
    assign product2_re = $signed(imA) * $signed(imB); 
    
    assign sum_re = accumulator_re + product1_re + product2_re;
    
    // Parte Imaginária
    assign product1_im = $signed(reA) * $signed(imB);
    
    assign product2_im = $signed(imA) * $signed(reB);
    
    assign sum_im = accumulator_im + product1_im + product2_im; 

	// Saída
	assign X = accumulator_re;
    assign Y = accumulator_im;
    
    always @(posedge clk) begin
        
		if (en) begin
            accumulator_re <= sum_re; 
            accumulator_im <= sum_im;
		end else if (rst) begin
            accumulator_re <= {WIDHT_OUT{1'b0}}; 
            accumulator_im <= {WIDHT_OUT{1'b0}};
		end else begin
            accumulator_re <= DEFAULT_RE; 
            accumulator_im <= DEFAULT_IM;
		end

    end

endmodule

CIDI-Modulos/SD142-CIRC-DIGITAIS-III/A-306/MAC_complex_tb.v
/*
Program: CI Digital T2/2025
Class: Circuito Digitais III 
Class-ID: SD142
Advisor: Felipe Rocha 
Advisor-Contact: felipef.rocha@inatel.br
Institute: INATEL - Santa Rita do Sapucaí / MG  
Development: André Bezerra 
Student-Contact: andrefrbezerra@gmail.com
Task-ID: A-306
Type: TestBench
Data: febuary, 03 2026
*/

`timescale 1 ns / 1 ps;

module MAC_complex_tb;

	// Parameters
	localparam WIDHT_IN = 8, WIDHT_OUT = 32, DELAY = 5, REPEAT = 10;

	//Ports
	reg 					clk, rst, en;
	reg	 [WIDHT_IN-1 : 0]	reA, reB, imA, imB;
	wire [WIDHT_OUT-1 : 0]	X,Y;

	integer seed1, seed2, seed3, seed4, i; 
	// [3:0] seed;  

	MAC_complex MAC_complex_testbench (
		.clk(clk), .rst(rst), .en(en),
		.reA(reA), .reB(reB),
		.imA(imA), .imB(imB),
		.X(X), .Y(Y)
	);

	always #DELAY  clk = !clk;
	
	always @(posedge clk) begin
		seed1 <= $time; 
		seed2 <= $time + 10; 
		seed3 <= $time + 20; 
		seed4 <= $time + 30; 
	end
	
	initial begin
		
		$dumpfile("CIDI-SD142-A306-B.vcd"); 
        $dumpvars(0, MAC_complex_tb); 
		
		$display("|A		|B		|Result		|";
		$monitor("(%d + j%d )*(%d +j%d) = (%d + j%d)", 
			reA, imA, reB, imB, X, Y
		); 
		
	end

	initial begin
	
		{clk, en, rst} <= {0,1,0}; 
		{reA, reB, imA, imB} <= {8'b0, 8'b0, 8'b0, 8'b0}; // [ ] Ajustar data   
		#DELAY; 

		{rst, en} <= {0, 1};

		for (i = 0; i < REPEAT; i = i + 1 ) begin
			
			@(posedge clk);
			reA <= $random(seed1) + $random(seed4);
			reB <= $random(seed2) + $random(seed3);
			imA <= $random(seed3);
			imB <= $random(seed4);   
			
			@(posedge clk);
			rst <= 1; 
			
			@(posedge clk);
			rst <= 0; 
		end 
		
		$finish;

	end
endmodule

CIDI-Modulos/SD142-CIRC-DIGITAIS-III/A-306/CIDI-SD142-A306-complex.vcd
$date
	Mon Feb 23 20:44:49 2026
$end
$version
	Icarus Verilog
$end
$timescale
	1ps
$end
$scope module MAC_complex_tb $end
$var wire 32 ! Y [31:0] $end
$var wire 32 " X [31:0] $end
$var parameter 32 # DELAY $end
$var parameter 32 $ REPEAT $end
$var parameter 32 % WIDHT_IN $end
$var parameter 32 & WIDHT_OUT $end
$var reg 1 ' clk $end
$var reg 1 ( en $end
$var reg 8 ) imA [7:0] $end
$var reg 8 * imB [7:0] $end
$var reg 8 + reA [7:0] $end
$var reg 8 , reB [7:0] $end
$var reg 1 - rst $end
$var integer 32 . i [31:0] $end
$var integer 32 / seed1 [31:0] $end
$var integer 32 0 seed2 [31:0] $end
$var integer 32 1 seed3 [31:0] $end
$var integer 32 2 seed4 [31:0] $end
$scope module MAC_complex_testbench $end
$var wire 32 3 X [31:0] $end
$var wire 32 4 Y [31:0] $end
$var wire 1 ' clk $end
$var wire 1 ( en $end
$var wire 8 5 imA [7:0] $end
$var wire 8 6 imB [7:0] $end
$var wire 8 7 reA [7:0] $end
$var wire 8 8 reB [7:0] $end
$var wire 1 - rst $end
$var wire 32 9 sum_re [31:0] $end
$var wire 32 : sum_im [31:0] $end
$var wire 16 ; product2_re [15:0] $end
$var wire 16 < product2_im [15:0] $end
$var wire 16 = product1_re [15:0] $end
$var wire 16 > product1_im [15:0] $end
$var parameter 32 ? DEFAULT_IM $end
$var parameter 32 @ DEFAULT_RE $end
$var parameter 32 A WIDHT_IN $end
$var parameter 32 B WIDHT_OUT $end
$var reg 32 C accumulator_im [31:0] $end
$var reg 32 D accumulator_re [31:0] $end
$upscope $end
$upscope $end
$enddefinitions $end
$comment Show the parameter values. $end
$dumpall
b100000 B
b1000 A
b0 @
b0 ?
b100000 &
b1000 %
b1100100 $
b101 #
$end
#0
$dumpvars
bx D
bx C
b0 >
b0 =
b0 <
b0 ;
bx :
bx 9
b0 8
b0 7
b0 6
b0 5
bx 4
bx 3
bx 2
bx 1
bx 0
bx /
bx .
1-
b0 ,
b0 +
b0 *
b0 )
0(
0'
bx "
bx !
$end
#5000
b0 :
b0 !
b0 4
b0 C
b0 9
b0 "
b0 3
b0 D
b100011 2
b11001 1
b1111 0
b101 /
0-
1(
b0 .
1'
#10000
0'
#15000
b1110111000000 9
b1110111000000 ;
b11000000 *
b11000000 6
b10001001 )
b10001001 5
b1 .
b100011 1
b11001 0
b101101 2
b1111 /
1'
#20000
0'
#25000
b1110111000000 "
b1110111000000 3
b1110111000000 D
b11110111 *
b11110111 6
b10000000000000 9
b1001000000 ;
b11000000 )
b11000000 5
b10 .
b101101 1
b100011 0
b110111 2
b11001 /
1'
#30000
0'
#35000
b101110 *
b101110 6
b1111111001100010 ;
b11110111 )
b11110111 5
b1111001100010 9
b10000000000000 "
b10000000000000 3
b10000000000000 D
b11 .
b110111 1
b101101 0
b1000001 2
b100011 /
1'
#40000
0'
#45000
b1111001100010 "
b1111001100010 3
b1111001100010 D
b1100100 *
b1100100 6
b11000001011010 9
b1000111111000 ;
b101110 )
b101110 5
b100 .
b1000001 1
b110111 0
b1001011 2
b101101 /
1'
#50000
0'
#55000
b10011011 *
b10011011 6
b1101100010001100 ;
b1100100 )
b1100100 5
b100011100110 9
b11000001011010 "
b11000001011010 3
b11000001011010 D
b101 .
b1001011 1
b1000001 0
b1010101 2
b110111 /
1'
#60000
0'
#65000
b100011100110 "
b100011100110 3
b100011100110 D
b11010010 *
b11010010 6
b1101100001100 9
b1001000100110 ;
b10011011 )
b10011011 5
b110 .
b1010101 1
b1001011 0
b1011111 2
b1000001 /
1'
#70000
0'
#75000
b1001 *
b1001 6
b1111111001100010 ;
b11010010 )
b11010010 5
b1100101101110 9
b1101100001100 "
b1101100001100 3
b1101100001100 D
b111 .
b1011111 1
b1010101 0
b1101001 2
b1001011 /
1'
#80000
0'
#85000
b1100101101110 "
b1100101101110 3
b1100101101110 D
b1000000 *
b1000000 6
b1101110101110 9
b1001000000 ;
b1001 )
b1001 5
b1000 .
b1101001 1
b1011111 0
b1110011 2
b1010101 /
1'
#90000
0'
#95000
b1110111 *
b1110111 6
b1110111000000 ;
b1000000 )
b1000000 5
b11100101101110 9
b1101110101110 "
b1101110101110 3
b1101110101110 D
b1001 .
b1110011 1
b1101001 0
b1111101 2
b1011111 /
1'
#100000
0'
#105000
b11100101101110 "
b11100101101110 3
b11100101101110 D
b10101110 *
b10101110 6
b1001101010000 9
b1101100111100010 ;
b1110111 )
b1110111 5
b11111111111111111111111110101110 :
b1111111110101110 >
b1 +
b1 7
b1010 .
b1111101 1
b1110011 0
b10000111 2
b1101001 /
1'
#110000
0'
#115000
b1111111111100101 >
b11100101 *
b11100101 6
b100010100110 ;
b10101110 )
b10101110 5
b1 =
b1111111110101110 <
b1 ,
b1 8
b11111111111111111111111101000001 :
b11111111111111111111111110101110 !
b11111111111111111111111110101110 4
b11111111111111111111111110101110 C
b1101111110111 9
b1001101010000 "
b1001101010000 3
b1001101010000 D
b1011 .
b10000111 1
b1111101 0
b10010001 2
b1110011 /
1'
#120000
0'
#125000
b11111111111111111111111101000001 !
b11111111111111111111111101000001 4
b11111111111111111111111101000001 C
b1101111110111 "
b1101111110111 3
b1101111110111 D
b11100 >
b11100 *
b11100 6
b1111110100001100 ;
b11100101 )
b11100101 5
b1100100000101 9
b10 =
b11111111111111111111111100100111 :
b1111111111001010 <
b10 ,
b10 8
b1100 .
b10010001 1
b10000111 0
b10011011 2
b1111101 /
1'
#130000
0'
#135000
b1010011 *
b1010011 6
b100100010100 ;
b111000 <
b11100 )
b11100 5
b100 =
b10100110 >
b10 +
b10 7
b101 :
b11111111111111111111111100100111 !
b11111111111111111111111100100111 4
b11111111111111111111111100100111 C
b10001000011101 9
b1100100000101 "
b1100100000101 3
b1100100000101 D
b1101 .
b10011011 1
b10010001 0
b10100101 2
b10000111 /
1'
#140000
0'
#145000
b101 !
b101 4
b101 C
b10001000011101 "
b10001000011101 3
b10001000011101 D
b1111111100010100 >
b10001010 *
b10001010 6
b11111111111111111111101111011111 9
b1101100110111110 ;
b11111111111111111111111110111111 :
b10100110 <
b1010011 )
b1010011 5
b1110 .
b10100101 1
b10011011 0
b10101111 2
b10010001 /
1'
#150000
0'
#155000
b1111111110000000 >
b11000000 *
b11000000 6
b1110110000000 ;
b1111111100010100 <
b10001010 )
b10001010 5
b11111111111111111111111001010011 :
b11111111111111111111111110111111 !
b11111111111111111111111110111111 4
b11111111111111111111111110111111 C
b1100101100011 9
b11111111111111111111101111011111 "
b11111111111111111111101111011111 3
b11111111111111111111101111011111 D
b1111 .
b10101111 1
b10100101 0
b10111001 2
b10011011 /
1'
#160000
0'
#165000
b11111111111111111111111001010011 !
b11111111111111111111111001010011 4
b11111111111111111111111001010011 C
b1100101100011 "
b1100101100011 3
b1100101100011 D
b1111111111101110 >
b11110111 *
b11110111 6
b1101110100111 9
b1001000000 ;
b11111111111111111111110111000001 :
b1111111110000000 <
b11000000 )
b11000000 5
b10000 .
b10111001 1
b10101111 0
b11000011 2
b10100101 /
1'
#170000
0'
#175000
b1011100 >
b101110 *
b101110 6
b1111111001100010 ;
b1111111111101110 <
b11110111 )
b11110111 5
b11111111111111111111111000001011 :
b11111111111111111111110111000001 !
b11111111111111111111110111000001 4
b11111111111111111111110111000001 C
b1101000001101 9
b1101110100111 "
b1101110100111 3
b1101110100111 D
b10001 .
b11000011 1
b10111001 0
b11001101 2
b10101111 /
1'
#180000
0'
#185000
b11111111111111111111111000001011 !
b11111111111111111111111000001011 4
b11111111111111111111111000001011 C
b1101000001101 "
b1101000001101 3
b1101000001101 D
b11001010 >
b1100101 *
b1100101 6
b10110000110111 9
b1001000100110 ;
b11111111111111111111111100110001 :
b1011100 <
b101110 )
b101110 5
b10010 .
b11001101 1
b11000011 0
b11010111 2
b10111001 /
1'
#190000
0'
#195000
b1111111100111000 >
b10011100 *
b10011100 6
b1101100010001100 ;
b11001010 <
b1100101 )
b1100101 5
b11111111111111111111111100110011 :
b11111111111111111111111100110001 !
b11111111111111111111111100110001 4
b11111111111111111111111100110001 C
b10011000111 9
b10110000110111 "
b10110000110111 3
b10110000110111 D
b10011 .
b11010111 1
b11001101 0
b11100001 2
b11000011 /
1'
#200000
0'
#205000
b11111111111111111111111100110011 !
b11111111111111111111111100110011 4
b11111111111111111111111100110011 C
b10011000111 "
b10011000111 3
b10011000111 D
b1111111110100110 >
b11010011 *
b11010011 6
b1011001011111 9
b1000110010100 ;
b11111111111111111111111000010001 :
b1111111100111000 <
b10011100 )
b10011100 5
b10100 .
b11100001 1
b11010111 0
b11101011 2
b11001101 /
1'
#210000
0'
#215000
b10100 >
b1010 *
b1010 6
b1111111000111110 ;
b1111111110100110 <
b11010011 )
b11010011 5
b11111111111111111111110111001011 :
b11111111111111111111111000010001 !
b11111111111111111111111000010001 4
b11111111111111111111111000010001 C
b1010010100001 9
b1011001011111 "
b1011001011111 3
b1011001011111 D
b10101 .
b11101011 1
b11100001 0
b11110101 2
b11010111 /
1'
#220000
0'
#225000
b11111111111111111111110111001011 !
b11111111111111111111110111001011 4
b11111111111111111111110111001011 C
b1010010100001 "
b1010010100001 3
b1010010100001 D
b1000001 *
b1000001 6
b1010001010 ;
b10100 <
b1010 )
b1010 5
b1011100110001 9
b110 =
b11111111111111111111111010100010 :
b11000011 >
b11 +
b11 7
b10110 .
b11110101 1
b11101011 0
b11111111 2
b11100001 /
1'
#230000
0'
#235000
b101101000 >
b1111000 *
b1111000 6
b1111001111000 ;
b1000001 )
b1000001 5
b1001 =
b11000011 <
b11 ,
b11 8
b11001101 :
b11111111111111111111111010100010 !
b11111111111111111111111010100010 4
b11111111111111111111111010100010 C
b11010110110010 9
b1011100110001 "
b1011100110001 3
b1011100110001 D
b10111 .
b11111111 1
b11110101 0
b100001001 2
b11101011 /
1'
#240000
0'
#245000
b11001101 !
b11001101 4
b11001101 C
b11010110110010 "
b11010110110010 3
b11010110110010 D
b1111111100001101 >
b10101111 *
b10101111 6
b1101101000001000 ;
b1111000 )
b1111000 5
b111111000110 9
b1100 =
b110111010 :
b111100000 <
b100 ,
b100 8
b11000 .
b100001001 1
b11111111 0
b100010011 2
b11110101 /
1'
#250000
0'
#255000
b11100110 *
b11100110 6
b100000111010 ;
b1111111010111100 <
b10101111 )
b10101111 5
b10000 =
b1111111110011000 >
b100 +
b100 7
b1110 :
b110111010 !
b110111010 4
b110111010 C
b1100000010000 9
b111111000110 "
b111111000110 3
b111111000110 D
b11001 .
b100010011 1
b100001001 0
b100011101 2
b11111111 /
1'
#260000
0'
#265000
b1110 !
b1110 4
b1110 C
b1100000010000 "
b1100000010000 3
b1100000010000 D
b1110000 >
b11100 *
b11100 6
b1010101001000 9
b1111110100101000 ;
b10110 :
b1111111110011000 <
b11100110 )
b11100110 5
b11010 .
b100011101 1
b100010011 0
b100100111 2
b100001001 /
1'
#270000
0'
#275000
b101001100 >
b1010011 *
b1010011 6
b100100010100 ;
b1110000 <
b11100 )
b11100 5
b111010010 :
b10110 !
b10110 4
b10110 C
b1111001101100 9
b1010101001000 "
b1010101001000 3
b1010101001000 D
b11011 .
b100100111 1
b100011101 0
b100110001 2
b100010011 /
1'
#280000
0'
#285000
b111010010 !
b111010010 4
b111010010 C
b1111001101100 "
b1111001101100 3
b1111001101100 D
b1111111000101000 >
b10001010 *
b10001010 6
b11111111111111111111100000111010 9
b1101100110111110 ;
b101000110 :
b101001100 <
b1010011 )
b1010011 5
b11100 .
b100110001 1
b100100111 0
b100111011 2
b100011101 /
1'
#290000
0'
#295000
b1111111100000100 >
b11000001 *
b11000001 6
b1110100001010 ;
b1111111000101000 <
b10001010 )
b10001010 5
b11111111111111111111111001110010 :
b101000110 !
b101000110 4
b101000110 C
b1010101010100 9
b11111111111111111111100000111010 "
b11111111111111111111100000111010 3
b11111111111111111111100000111010 D
b11101 .
b100111011 1
b100110001 0
b101000101 2
b100100111 /
1'
#300000
0'
#305000
b11111111111111111111111001110010 !
b11111111111111111111111001110010 4
b11111111111111111111111001110010 C
b1010101010100 "
b1010101010100 3
b1010101010100 D
b1111111111100000 >
b11111000 *
b11111000 6
b1011101011100 9
b111111000 ;
b11111111111111111111110101010110 :
b1111111100000100 <
b11000001 )
b11000001 5
b11110 .
b101000101 1
b100111011 0
b101001111 2
b100110001 /
1'
#310000
0'
#315000
b10111100 >
b101111 *
b101111 6
b1111111010001000 ;
b1111111111100000 <
b11111000 )
b11111000 5
b11111111111111111111110111110010 :
b11111111111111111111110101010110 !
b11111111111111111111110101010110 4
b11111111111111111111110101010110 C
b1010111110100 9
b1011101011100 "
b1011101011100 3
b1011101011100 D
b11111 .
b101001111 1
b101000101 0
b101011001 2
b100111011 /
1'
#320000
0'
#325000
b11111111111111111111110111110010 !
b11111111111111111111110111110010 4
b11111111111111111111110111110010 C
b1010111110100 "
b1010111110100 3
b1010111110100 D
b110011000 >
b1100110 *
b1100110 6
b10100010111110 9
b1001010111010 ;
b1000110 :
b10111100 <
b101111 )
b101111 5
b100000 .
b101011001 1
b101001111 0
b101100011 2
b101000101 /
1'
#330000
0'
#335000
b1111111001110100 >
b10011101 *
b10011101 6
b1101100010001110 ;
b110011000 <
b1100110 )
b1100110 5
b1010010 :
b1000110 !
b1000110 4
b1000110 C
b101011100 9
b10100010111110 "
b10100010111110 3
b10100010111110 D
b100001 .
b101100011 1
b101011001 0
b101101101 2
b101001111 /
1'
#340000
0'
#345000
b1010010 !
b1010010 4
b1010010 C
b101011100 "
b101011100 3
b101011100 D
b11010100 *
b11010100 6
b1000100000100 ;
b1111111001110100 <
b10011101 )
b10011101 5
b1001001110100 9
b10100 =
b11111111111111111111110111101010 :
b1111111100100100 >
b101 +
b101 7
b100010 .
b101101101 1
b101100011 0
b101110111 2
b101011001 /
1'
#350000
0'
#355000
b110111 >
b1011 *
b1011 6
b1111111000011100 ;
b11010100 )
b11010100 5
b11001 =
b1111111100100100 <
b101 ,
b101 8
b11111111111111111111110101000101 :
b11111111111111111111110111101010 !
b11111111111111111111110111101010 4
b11111111111111111111110111101010 C
b1000010101001 9
b1001001110100 "
b1001001110100 3
b1001001110100 D
b100011 .
b101110111 1
b101101101 0
b110000001 2
b101100011 /
1'
#360000
0'
#365000
b11111111111111111111110101000101 !
b11111111111111111111110101000101 4
b11111111111111111111110101000101 C
b1000010101001 "
b1000010101001 3
b1000010101001 D
b101001010 >
b1000010 *
b1000010 6
b1011010110 ;
b1011 )
b1011 5
b1001110011101 9
b11110 =
b11111111111111111111111011010001 :
b1000010 <
b110 ,
b110 8
b100100 .
b110000001 1
b101110111 0
b110001011 2
b101101101 /
1'
#370000
0'
#375000
b1111000 *
b1111000 6
b1111011110000 ;
b110001100 <
b1000010 )
b1000010 5
b100100 =
b1011010000 >
b110 +
b110 7
b1100101101 :
b11111111111111111111111011010001 !
b11111111111111111111111011010001 4
b11111111111111111111111011010001 C
b11001010110001 9
b1001110011101 "
b1001110011101 3
b1001110011101 D
b100101 .
b110001011 1
b110000001 0
b110010101 2
b101110111 /
1'
#380000
0'
#385000
b1100101101 !
b1100101101 4
b1100101101 C
b11001010110001 "
b11001010110001 3
b11001010110001 D
b1111111000011010 >
b10101111 *
b10101111 6
b110011011101 9
b1101101000001000 ;
b10000010111 :
b1011010000 <
b1111000 )
b1111000 5
b100110 .
b110010101 1
b110001011 0
b110011111 2
b110000001 /
1'
#390000
0'
#395000
b1111111101100100 >
b11100110 *
b11100110 6
b100000111010 ;
b1111111000011010 <
b10101111 )
b10101111 5
b110010101 :
b10000010111 !
b10000010111 4
b10000010111 C
b1010100111011 9
b110011011101 "
b110011011101 3
b110011011101 D
b100111 .
b110011111 1
b110010101 0
b110101001 2
b110001011 /
1'
#400000
0'
#405000
b110010101 !
b110010101 4
b110010101 C
b1010100111011 "
b1010100111011 3
b1010100111011 D
b10101110 >
b11101 *
b11101 6
b1001001101101 9
b1111110100001110 ;
b110100111 :
b1111111101100100 <
b11100110 )
b11100110 5
b101000 .
b110101001 1
b110011111 0
b110110011 2
b110010101 /
1'
#410000
0'
#415000
b111111000 >
b1010100 *
b1010100 6
b100110000100 ;
b10101110 <
b11101 )
b11101 5
b10001001101 :
b110100111 !
b110100111 4
b110100111 C
b1110000010101 9
b1001001101101 "
b1001001101101 3
b1001001101101 D
b101001 .
b110110011 1
b110101001 0
b110111101 2
b110011111 /
1'
#420000
0'
#425000
b10001001101 !
b10001001101 4
b10001001101 C
b1110000010101 "
b1110000010101 3
b1110000010101 D
b1111110101000010 >
b10001011 *
b10001011 6
b11111111111111111111010111010101 9
b1101100110011100 ;
b1110000111 :
b111111000 <
b1010100 )
b1010100 5
b101010 .
b110111101 1
b110110011 0
b111000111 2
b110101001 /
1'
#430000
0'
#435000
b1111111010001100 >
b11000010 *
b11000010 6
b1110001010110 ;
b1111110101000010 <
b10001011 )
b10001011 5
b11111111111111111111111101010101 :
b1110000111 !
b1110000111 4
b1110000111 C
b1001001001111 9
b11111111111111111111010111010101 "
b11111111111111111111010111010101 3
b11111111111111111111010111010101 D
b101011 .
b111000111 1
b110111101 0
b111010001 2
b110110011 /
1'
#440000
0'
#445000
b11111111111111111111111101010101 !
b11111111111111111111111101010101 4
b11111111111111111111111101010101 C
b1001001001111 "
b1001001001111 3
b1001001001111 D
b1111111111010110 >
b11111001 *
b11111001 6
b1010000100101 9
b110110010 ;
b11111111111111111111110110110111 :
b1111111010001100 <
b11000010 )
b11000010 5
b101100 .
b111010001 1
b111000111 0
b111011011 2
b110111101 /
1'
#450000
0'
#455000
b100100000 >
b110000 *
b110000 6
b1111111010110000 ;
b1111111111010110 <
b11111001 )
b11111001 5
b11111111111111111111111010101101 :
b11111111111111111111110110110111 !
b11111111111111111111110110110111 4
b11111111111111111111110110110111 C
b1001011111001 9
b1010000100101 "
b1010000100101 3
b1010000100101 D
b101101 .
b111011011 1
b111010001 0
b111100101 2
b111000111 /
1'
#460000
0'
#465000
b11111111111111111111111010101101 !
b11111111111111111111111010101101 4
b11111111111111111111111010101101 C
b1001011111001 "
b1001011111001 3
b1001011111001 D
b1001101010 >
b1100111 *
b1100111 6
b10011001101101 9
b1001101010000 ;
b1000110111 :
b100100000 <
b110000 )
b110000 5
b101110 .
b111100101 1
b111011011 0
b111101111 2
b111010001 /
1'
#470000
0'
#475000
b10011110 *
b10011110 6
b1101100010010010 ;
b1001101010 <
b1100111 )
b1100111 5
b101010 =
b1111110101010010 >
b111 +
b111 7
b111110011 :
b1000110111 !
b1000110111 4
b1000110111 C
b11111111111111111111111100101001 9
b10011001101101 "
b10011001101101 3
b10011001101101 D
b101111 .
b111101111 1
b111100101 0
b111111001 2
b111011011 /
1'
#480000
0'
#485000
b111110011 !
b111110011 4
b111110011 C
b11111111111111111111111100101001 "
b11111111111111111111111100101001 3
b11111111111111111111111100101001 D
b1111111011010011 >
b11010101 *
b11010101 6
b1000001110110 ;
b10011110 )
b10011110 5
b111111010000 9
b110001 =
b11111111111111111111111000011000 :
b1111110101010010 <
b111 ,
b111 8
b110000 .
b111111001 1
b111101111 0
b1000000011 2
b111100101 /
1'
#490000
0'
#495000
b1001101 >
b1011 *
b1011 6
b1111111000100111 ;
b11010101 )
b11010101 5
b111000 =
b1111111010101000 <
b1000 ,
b1000 8
b11111111111111111111110100001101 :
b11111111111111111111111000011000 !
b11111111111111111111111000011000 4
b11111111111111111111111000011000 C
b111000101111 9
b111111010000 "
b111111010000 3
b111111010000 D
b110001 .
b1000000011 1
b111111001 0
b1000001101 2
b111101111 /
1'
#500000
0'
#505000
b11111111111111111111110100001101 !
b11111111111111111111110100001101 4
b11111111111111111111110100001101 C
b111000101111 "
b111000101111 3
b111000101111 D
b1000010 *
b1000010 6
b1011010110 ;
b1011000 <
b1011 )
b1011 5
b1000101000101 9
b1000000 =
b11111111111111111111111101110101 :
b1000010000 >
b1000 +
b1000 7
b110010 .
b1000001101 1
b1000000011 0
b1000010111 2
b111111001 /
1'
#510000
0'
#515000
b1111001000 >
b1111001 *
b1111001 6
b1111100110010 ;
b1000010000 <
b1000010 )
b1000010 5
b10101001101 :
b11111111111111111111111101110101 !
b11111111111111111111111101110101 4
b11111111111111111111111101110101 C
b11000010110111 9
b1000101000101 "
b1000101000101 3
b1000101000101 D
b110011 .
b1000010111 1
b1000001101 0
b1000100001 2
b1000000011 /
1'
#520000
0'
#525000
b10101001101 !
b10101001101 4
b10101001101 C
b11000010110111 "
b11000010110111 3
b11000010110111 D
b1111110110000000 >
b10110000 *
b10110000 6
b101100100111 9
b1101101000110000 ;
b11010010101 :
b1111001000 <
b1111001 )
b1111001 5
b110100 .
b1000100001 1
b1000010111 0
b1000101011 2
b1000001101 /
1'
#530000
0'
#535000
b1111111100111000 >
b11100111 *
b11100111 6
b11111010000 ;
b1111110110000000 <
b10110000 )
b10110000 5
b1101001101 :
b11010010101 !
b11010010101 4
b11010010101 C
b1001100110111 9
b101100100111 "
b101100100111 3
b101100100111 D
b110101 .
b1000101011 1
b1000100001 0
b1000110101 2
b1000010111 /
1'
#540000
0'
#545000
b1101001101 !
b1101001101 4
b1101001101 C
b1001100110111 "
b1001100110111 3
b1001100110111 D
b11110000 >
b11110 *
b11110 6
b1000010001001 9
b1111110100010010 ;
b1101110101 :
b1111111100111000 <
b11100111 )
b11100111 5
b110110 .
b1000110101 1
b1000101011 0
b1000111111 2
b1000100001 /
1'
#550000
0'
#555000
b1010101000 >
b1010101 *
b1010101 6
b100111110110 ;
b11110000 <
b11110 )
b11110 5
b11100001101 :
b1101110101 !
b1101110101 4
b1101110101 C
b1101010111111 9
b1000010001001 "
b1000010001001 3
b1000010001001 D
b110111 .
b1000111111 1
b1000110101 0
b1001001001 2
b1000101011 /
1'
#560000
0'
#565000
b11100001101 !
b11100001101 4
b11100001101 C
b1101010111111 "
b1101010111111 3
b1101010111111 D
b1111110001100000 >
b10001100 *
b10001100 6
b11111111111111111111010001111011 9
b1101100101111100 ;
b11000010101 :
b1010101000 <
b1010101 )
b1010101 5
b111000 .
b1001001001 1
b1000111111 0
b1001010011 2
b1000110101 /
1'
#570000
0'
#575000
b1111111000011000 >
b11000011 *
b11000011 6
b1101110100100 ;
b1111110001100000 <
b10001100 )
b10001100 5
b10001101 :
b11000010101 !
b11000010101 4
b11000010101 C
b1000001011111 9
b11111111111111111111010001111011 "
b11111111111111111111010001111011 3
b11111111111111111111010001111011 D
b111001 .
b1001010011 1
b1001001001 0
b1001011101 2
b1000111111 /
1'
#580000
0'
#585000
b10001101 !
b10001101 4
b10001101 C
b1000001011111 "
b1000001011111 3
b1000001011111 D
b1111111111010000 >
b11111010 *
b11111010 6
b1001000001101 9
b101101110 ;
b11111111111111111111111001110101 :
b1111111000011000 <
b11000011 )
b11000011 5
b111010 .
b1001011101 1
b1001010011 0
b1001100111 2
b1001001001 /
1'
#590000
0'
#595000
b110001 *
b110001 6
b1111111011011010 ;
b1111111111010000 <
b11111010 )
b11111010 5
b1001000 =
b110111001 >
b1001 +
b1001 7
b11111111111111111111111111111110 :
b11111111111111111111111001110101 !
b11111111111111111111111001110101 4
b11111111111111111111111001110101 C
b1000100101111 9
b1001000001101 "
b1001000001101 3
b1001000001101 D
b111011 .
b1001100111 1
b1001011101 0
b1001110001 2
b1001010011 /
1'
#600000
0'
#605000
b11111111111111111111111111111110 !
b11111111111111111111111111111110 4
b11111111111111111111111111111110 C
b1000100101111 "
b1000100101111 3
b1000100101111 D
b1110011111 >
b1100111 *
b1100111 6
b1001110110111 ;
b110001 )
b110001 5
b10010100110111 9
b1010001 =
b10101010110 :
b110111001 <
b1001 ,
b1001 8
b111100 .
b1001110001 1
b1001100111 0
b1001111011 2
b1001011101 /
1'
#610000
0'
#615000
b1111110010001110 >
b10011110 *
b10011110 6
b1101100010010010 ;
b1100111 )
b1100111 5
b1011010 =
b10000000110 <
b1010 ,
b1010 8
b10111101010 :
b10101010110 !
b10101010110 4
b10101010110 C
b11111111111111111111111000100011 9
b10010100110111 "
b10010100110111 3
b10010100110111 D
b111101 .
b1001111011 1
b1001110001 0
b1010000101 2
b1001100111 /
1'
#620000
0'
#625000
b10111101010 !
b10111101010 4
b10111101010 C
b11111111111111111111111000100011 "
b11111111111111111111111000100011 3
b11111111111111111111111000100011 D
b11010101 *
b11010101 6
b1000001110110 ;
b1111110000101100 <
b10011110 )
b10011110 5
b111011111101 9
b1100100 =
b1101000 :
b1111111001010010 >
b1010 +
b1010 7
b111110 .
b1010000101 1
b1001111011 0
b1010001111 2
b1001110001 /
1'
#630000
0'
#635000
b1111000 >
b1100 *
b1100 6
b1111110111111100 ;
b1111111001010010 <
b11010101 )
b11010101 5
b11111111111111111111111100110010 :
b1101000 !
b1101000 4
b1101000 C
b110101011101 9
b111011111101 "
b111011111101 3
b111011111101 D
b111111 .
b1010001111 1
b1010000101 0
b1010011001 2
b1001111011 /
1'
#640000
0'
#645000
b11111111111111111111111100110010 !
b11111111111111111111111100110010 4
b11111111111111111111111100110010 C
b110101011101 "
b110101011101 3
b110101011101 D
b1010011110 >
b1000011 *
b1000011 6
b1000011100101 9
b1100100100 ;
b1001001000 :
b1111000 <
b1100 )
b1100 5
b1000000 .
b1010011001 1
b1010001111 0
b1010100011 2
b1010000101 /
1'
#650000
0'
#655000
b10011000100 >
b1111010 *
b1111010 6
b1111111101110 ;
b1010011110 <
b1000011 )
b1000011 5
b100110101010 :
b1001001000 !
b1001001000 4
b1001001000 C
b11000100110111 9
b1000011100101 "
b1000011100101 3
b1000011100101 D
b1000001 .
b1010100011 1
b1010011001 0
b1010101101 2
b1010001111 /
1'
#660000
0'
