CIDI-Modulos/SD122-CIRC-DIGITAIS-I/SD122-Task-2/A102-1/task-2/bcd_to_ex3.v
/*
Program: CI Digital T2/2025
Class: Introdução à Verilog  
Class-ID: SD122
Advisor: Felipe Rocha 
Advisor-Contact: felipef.rocha@inatel.br
Institute: INATEL - Santa Rita do Sapucaí / MG  
Development: André Bezerra 
Student-Contact: andrefrbezerra@gmail.com
Task-ID: A-102-1
Type: Laboratory
Data: octuber, 17 2025
*/

`timescale 1 ns / 1 ps;

/*
	S3 = A + B·C + B·D   = A + B·(C + D)
	S2 = B ⊕ (C + D)     = B XOR (C OR D)
	S1 = C·D + ¬C·¬D     = C XNOR D // equivalente a ~(C ^ D)
	S0 = ¬D
*/

module bcd_to_ex3(
	input a,b,c,d,
	output s0, s1, s2, s3
);

	assign s3 = a | (b & (c | d));
	assign s2 = b ^ (c | d);      // ^ XOR
	assign s1 = ~(c ^ d);         // >> XNOR
	assign s0 = ~d;

endmodule

CIDI-Modulos/SD122-CIRC-DIGITAIS-I/SD122-Task-2/A102-1/task-2/bcd_to_ec3_tb.v
/*
Program: CI Digital T2/2025
Class: Introdução à Verilog  
Class-ID: SD122
Advisor: Felipe Rocha 
Advisor-Contact: felipef.rocha@inatel.br
Institute: INATEL - Santa Rita do Sapucaí / MG  
Development: André Bezerra 
Student-Contact: andrefrbezerra@gmail.com
Task-ID: A-102-1
Type: Testbench
Data: octuber, 17 2025
*/

`timescale 1 ns / 1 ps;

module bcd_to_ec3_tb();

	localparam DELAY = 10, SAMPLES = 10; 
	reg a,b,c,d;
	wire s0, s1, s2, s3; // [3:0] s

	integer i;

	bcd_to_ex3 upp(
        	.a(a), .b(b), .c(c), .d(d),
		.s0(s0), .s1(s1), .s2(s2), .s3(s3)
	);

	initial begin
        
        	$dumpfile("CIDI-SD122-A102-1-2.vcd");
		$dumpvars(0, bcd_to_ec3_tb);

		$display("|A B C D	|S3 S2 S1 S0	|");
		
		$monitor("|%b %b %b %b	|%b  %b  %b  %b	|", a, b, c, d, s3, s2, s1, s0);

		for (i = 0; i < SAMPLES; i = i + 1) begin
			{a, b, c, d} = i[3:0];
			#DELAY;
		end
		$finish;
	end

endmodule

CIDI-Modulos/SD122-CIRC-DIGITAIS-I/SD122-Task-2/A102-1/task-2/CIDI-SD122-A102-1-2.vcd
$date
	Mon Nov 24 10:35:59 2025
$end
$version
	Icarus Verilog
$end
$timescale
	1ps
$end
$scope module bcd_to_ec3_tb $end
$var wire 1 ! s3 $end
$var wire 1 " s2 $end
$var wire 1 # s1 $end
$var wire 1 $ s0 $end
$var parameter 32 % DELAY $end
$var parameter 32 & SAMPLES $end
$var reg 1 ' a $end
$var reg 1 ( b $end
$var reg 1 ) c $end
$var reg 1 * d $end
$var integer 32 + i [31:0] $end
$scope module upp $end
$var wire 1 ' a $end
$var wire 1 ( b $end
$var wire 1 ) c $end
$var wire 1 * d $end
$var wire 1 $ s0 $end
$var wire 1 # s1 $end
$var wire 1 " s2 $end
$var wire 1 ! s3 $end
$upscope $end
$upscope $end
$enddefinitions $end
$comment Show the parameter values. $end
$dumpall
b1010 &
b1010 %
$end
#0
$dumpvars
b0 +
0*
0)
0(
0'
1$
1#
0"
0!
$end
#10000
1"
0#
0$
1*
b1 +
#20000
1$
1)
0*
b10 +
#30000
1#
0$
1*
b11 +
#40000
1$
1(
0)
0*
b100 +
#50000
1!
0"
0#
0$
1*
b101 +
#60000
1$
1)
0*
b110 +
#70000
1#
0$
1*
b111 +
#80000
1$
1'
0(
0)
0*
b1000 +
#90000
1"
0#
0$
1*
b1001 +
#100000
b1010 +
