CIDI-Modulos/SD122-CIRC-DIGITAIS-I/SD122-Task-2/A102-2/task-2/binary_grey.v
/*
Program: CI Digital T2/2025
Class: Introdução à Verilog  
Class-ID: SD122
Advisor: Felipe Rocha 
Advisor-Contact: felipef.rocha@inatel.br
Institute: INATEL - Santa Rita do Sapucaí / MG  
Development: André Bezerra 
Student-Contact: andrefrbezerra@gmail.com
Task-ID: A-102-2
Type: Laboratory
Data: november, 5 2025
*/

`timescale 1 ns / 1 ps;

module conversor_binario_grey(
	input 		[3:0] binario,
	output reg 	[3:0] gray
); // bcd_5311 para bcd_8421

	always@(*) begin
	    case(binario) // entrada -> bcd_8421
			4'b0000: gray = 4'b0000;
			4'b0001: gray = 4'b0001;
			4'b0010: gray = 4'b0011;
			4'b0011: gray = 4'b0010;
			4'b0100: gray = 4'b0110;
			4'b0101: gray = 4'b0111;
			4'b0110: gray = 4'b0101;
			4'b0111: gray = 4'b0100;
			4'b1000: gray = 4'b1100;
			4'b1001: gray = 4'b1101;
			4'b1010: gray = 4'b1111;
			4'b1011: gray = 4'b1110;
			4'b1100: gray = 4'b1010;
			4'b1101: gray = 4'b1011;
			4'b1110: gray = 4'b1001;
			4'b1111: gray = 4'b1000;
			default: gray = 4'bxxxx;
	    endcase
	end
endmodule

CIDI-Modulos/SD122-CIRC-DIGITAIS-I/SD122-Task-2/A102-2/task-2/binary_grey_tb.v
/*
Program: CI Digital T2/2025
Class: Introdução à Verilog  
Class-ID: SD122
Advisor: Felipe Rocha 
Advisor-Contact: felipef.rocha@inatel.br
Institute: INATEL - Santa Rita do Sapucaí / MG  
Development: André Bezerra 
Student-Contact: andrefrbezerra@gmail.com
Task-ID: A-102-2
Type: Testbench
Data: november, 5 2025
*/

`timescale 1ns/1ps

module conversor_binary_grey_tb();

	localparam DELAY = 10;
    reg [3:0] binario;
    wire [3:0] gray;

    conversor_binario_grey GREY_TB(
        .binario(binario),
        .gray(gray)
    );

    initial begin
    	
    	$dumpfile("CIDI-SD122-A102-3-1.vcd");
	$dumpvars(0, conversor_binary_grey_tb);

	$display(">|Binary	|Gray code	|");
	$monitor(" |%b		|%b		|", binario, gray);
		
        binario = 4'b0000; #DELAY;
        binario = 4'b0001; #DELAY;
        binario = 4'b0010; #DELAY;
        binario = 4'b0011; #DELAY;
        binario = 4'b0100; #DELAY;
        binario = 4'b0101; #DELAY;
        binario = 4'b0110; #DELAY;
        binario = 4'b0111; #DELAY;
        binario = 4'b1000; #DELAY;
        binario = 4'b1001; #DELAY;
        binario = 4'b1010; #DELAY;
        binario = 4'b1011; #DELAY;
        binario = 4'b1100; #DELAY;
        binario = 4'b1101; #DELAY;
        binario = 4'b1110; #DELAY;
        binario = 4'b1111; #DELAY;
        
        $finish;
    end
    

endmodule

CIDI-Modulos/SD122-CIRC-DIGITAIS-I/SD122-Task-2/A102-2/task-2/CIDI-SD122-A102-3.vcd
$date
	Mon Nov 24 17:17:38 2025
$end
$version
	Icarus Verilog
$end
$timescale
	1ps
$end
$scope module conversor_binary_grey_tb $end
$var wire 4 ! gray [3:0] $end
$var parameter 32 " DELAY $end
$var reg 4 # binario [3:0] $end
$scope module GREY_TB $end
$var wire 4 $ binario [3:0] $end
$var reg 4 % gray [3:0] $end
$upscope $end
$upscope $end
$enddefinitions $end
$comment Show the parameter values. $end
$dumpall
b1010 "
$end
#0
$dumpvars
b0 %
b0 $
b0 #
b0 !
$end
#10000
b1 !
b1 %
b1 #
b1 $
#20000
b11 !
b11 %
b10 #
b10 $
#30000
b10 !
b10 %
b11 #
b11 $
#40000
b110 !
b110 %
b100 #
b100 $
#50000
b111 !
b111 %
b101 #
b101 $
#60000
b101 !
b101 %
b110 #
b110 $
#70000
b100 !
b100 %
b111 #
b111 $
#80000
b1100 !
b1100 %
b1000 #
b1000 $
#90000
b1101 !
b1101 %
b1001 #
b1001 $
#100000
b1111 !
b1111 %
b1010 #
b1010 $
#110000
b1110 !
b1110 %
b1011 #
b1011 $
#120000
b1010 !
b1010 %
b1100 #
b1100 $
#130000
b1011 !
b1011 %
b1101 #
b1101 $
#140000
b1001 !
b1001 %
b1110 #
b1110 $
#150000
b1000 !
b1000 %
b1111 #
b1111 $
