CIDI-Modulos/SD122-CIRC-DIGITAIS-I/SD122-Task-12/task-4/ula.v
/*
Program: CI Digital T2/2025
Class: Circuito Digitais I 
Class-ID: SD122
Advisor: Felipe Rocha 
Advisor-Contact: felipef.rocha@inatel.br
Institute: INATEL - Santa Rita do Sapucaí / MG  
Development: André Bezerra 
Student-Contact: andrefrbezerra@gmail.com
Task-ID: A-112
Type: Laboratory
Data: november, 20 2025
*/

`timescale 1 ns / 1 ps;

module ula (
    input  		[3:0]	A, B,
    input				carry_in,
    input  		[2:0]	seletor,
    output reg	[3:0]	resultado,
    output reg			carry_out, 
    output 				Z
);
    always @(*) begin
        // Resetando os sinais de saída
        carry_out = 1'b0;
        resultado = 4'b0000;

        // Operações baseadas no seletor
        case (seletor)
            3'b000: resultado = A & B;    // AND
            3'b001: resultado = A | B;    // OR
            3'b010: resultado = ~A;       // NOT A
            3'b011: resultado = ~(A & B); // NAND
            3'b100: begin                 // Soma
                {carry_out, resultado} = A + B + carry_in;  // Soma com carry
            	end
            3'b101: begin                 // Subtração
                {carry_out, resultado} = {1'b0, A} - {1'b0, B} - carry_in; 
                // Subtração com carry
                carry_out = ~carry_out;   
            	end
            default: resultado = {4{1'b0}}; // Caso padrão (resultado zero)
        endcase
	end
    
    assign Z = resultado==0; 
    
endmodule

CIDI-Modulos/SD122-CIRC-DIGITAIS-I/SD122-Task-12/task-4/ula_tb.v
/*
Program: CI Digital T2/2025
Class: Circuito Digitais I 
Class-ID: SD122
Advisor: Felipe Rocha 
Advisor-Contact: felipef.rocha@inatel.br
Institute: INATEL - Santa Rita do Sapucaí / MG  
Development: André Bezerra 
Student-Contact: andrefrbezerra@gmail.com
Task-ID: A-112
Type: Testbench
Data: november, 20 2025
*/

`timescale 1 ns / 1 ps;

module ula_tb;
	localparam DELAY = 10; 
    reg [3:0] A, B;
    reg cin;
    reg [2:0] seletor;
    wire [3:0] resultado;
    wire carry_out, Z;

    ula DUT (
        .A(A), .B(B), .carry_in(cin), .seletor(seletor),
        .resultado(resultado), .carry_out(carry_out), .Z(Z)
    );
	
	initial begin
		
		$dumpfile("CIDI-SD122-A112-4.vcd");
        $dumpvars(0, ula_tb);

		$display("|A	|B	|Cin|Select	|Result	|Z |");
		$monitor("|%b	|%b	|%b  |%b	|%b	|%b |",
			A, B, cin, seletor, resultado, Z
		);
	end

    initial begin

        seletor = 3'b100;
		cin = 0;
		
		A = 4'b0000; B = 4'b0000;  
		#DELAY;

		A = 4'b0001; B = 4'b0001; 
		#DELAY;

		A = 4'b0011; B = 4'b0101;
		#DELAY;

		cin = 1;
		A = 4'b1010; B = 4'b0101;  
		#DELAY;

		A = 4'b1111; B = 4'b1111;
		#DELAY;

		seletor = 3'b000; 
		A = 4'b1010; B = 4'b1100; 
		#DELAY;

		seletor = 3'b001; 
		A = 4'b0011; B = 4'b0101; 
		#DELAY;

		seletor = 3'b101; 
		A = 4'b1001; B = 4'b0100;
		#DELAY;

        $finish;
    end
endmodule

CIDI-Modulos/SD122-CIRC-DIGITAIS-I/SD122-Task-12/task-4/CIDI-SD122-A112-4.vcd
$date
	Fri Dec  5 16:24:17 2025
$end
$version
	Icarus Verilog
$end
$timescale
	1ps
$end
$scope module ula_tb $end
$var wire 4 ! resultado [3:0] $end
$var wire 1 " carry_out $end
$var wire 1 # Z $end
$var parameter 32 $ DELAY $end
$var reg 4 % A [3:0] $end
$var reg 4 & B [3:0] $end
$var reg 1 ' cin $end
$var reg 3 ( seletor [2:0] $end
$scope module DUT $end
$var wire 4 ) A [3:0] $end
$var wire 4 * B [3:0] $end
$var wire 1 ' carry_in $end
$var wire 3 + seletor [2:0] $end
$var wire 1 # Z $end
$var reg 1 " carry_out $end
$var reg 4 , resultado [3:0] $end
$upscope $end
$upscope $end
$enddefinitions $end
$comment Show the parameter values. $end
$dumpall
b1010 $
$end
#0
$dumpvars
b0 ,
b100 +
b0 *
b0 )
b100 (
0'
b0 &
b0 %
1#
0"
b0 !
$end
#10000
0#
b10 !
b10 ,
b1 &
b1 *
b1 %
b1 )
#20000
0#
b1000 !
b1000 ,
b101 &
b101 *
b11 %
b11 )
#30000
1"
1#
b0 !
b0 ,
b1010 %
b1010 )
1'
#40000
0#
b1111 !
b1111 ,
1"
b1111 &
b1111 *
b1111 %
b1111 )
#50000
0#
b1000 !
b1000 ,
0"
b1100 &
b1100 *
b1010 %
b1010 )
b0 (
b0 +
#60000
0#
b111 !
b111 ,
b101 &
b101 *
b11 %
b11 )
b1 (
b1 +
#70000
1"
0#
b100 !
b100 ,
b100 &
b100 *
b1001 %
b1001 )
b101 (
b101 +
