CIDI-Modulos/SD122-CIRC-DIGITAIS-I/SD122-Task-12/task-2/ula_shift.v
/*
Program: CI Digital T2/2025
Class: Circuito Digitais I 
Class-ID: SD122
Advisor: Felipe Rocha 
Advisor-Contact: felipef.rocha@inatel.br
Institute: INATEL - Santa Rita do Sapucaí / MG  
Development: André Bezerra 
Student-Contact: andrefrbezerra@gmail.com
Task-ID: A-112
Type: Laboratory
Data: november, 20 2025
*/

`timescale 1 ns / 1 ps;

module ula_shift(
    input [3:0] A, B,
    input [2:0] sel,
    output reg [3:0] resultado
);
    always @(*) begin
        case (sel)
            3'b000: resultado = A & B;       // AND
            3'b001: resultado = A | B;       // OR
            3'b010: resultado = ~A;          // NOT (Apenas ao operando A)
            3'b011: resultado = ~(A & B);    // NAND
            3'b100: resultado = A + B;       // Soma
            3'b101: resultado = A - B;       // Subtração
            // Operacoes adicinais
            3'b110: resultado = A << 1;
            3'b111: resultado = A >> 1;
            default: resultado = 4'b0000;    // Padrão (zero)
        endcase
    end

endmodule

CIDI-Modulos/SD122-CIRC-DIGITAIS-I/SD122-Task-12/task-2/ula_shift_tb.v
/*
Program: CI Digital 02/2025
Class: Circuito Digitais I 
Class-ID: SD122
Advisor: Felipe Rocha 
Advisor-Contact: felipef.rocha@inatel.br
Institute: INATEL - Santa Rita do Sapucaí / MG  
Development: André Bezerra 
Student-Contact: andrefrbezerra@gmail.com
Task-ID: A-112
Type: Testbench
Data: november, 20 2025
*/

`timescale 1 ns / 1 ps;

module ula_shift_tb;

	localparam DELAY = 10;
    reg [3:0] A, B;
    reg [2:0] seletor;
    wire [3:0] resultado;

    ula_shift UUT (
        .A(A), .B(B), .sel(seletor),
        .resultado(resultado)
    );

	initial begin
			
			$dumpfile("CIDI-SD122-A112-2.vcd"); 
		    $dumpvars(0, ula_shift_tb); 
			
			$display("|A	|B	|Select	|Result	|");
			$monitor("|%b	|%b	|%b	|%b	|", A, B, seletor, resultado);
	end
	
	initial begin
		
		A = 4'b0000;
		B = 4'b0000;
		seletor = 3'b000;
		#DELAY;

		A = 4'b0010;
		B = 4'b0001;
		seletor = 3'b000;
		#DELAY;

		A = 4'b1100;
		B = 4'b1010;
		seletor = 3'b000;
		#DELAY;


		A = 4'b0101;
		B = 4'b0011;
		seletor = 3'b001;
		#DELAY;

		A = 4'b1111;
		B = 4'b0001;
		seletor = 3'b001;
		#DELAY;

		A = 4'b1001;
		B = 4'b1001;
		seletor = 3'b001;
		#DELAY;


		A = 4'b0011;
		B = 4'b0001;
		seletor = 3'b010;
		#DELAY;

		A = 4'b0101;
		B = 4'b0101;
		seletor = 3'b010;
		#DELAY;

		A = 4'b1111;
		B = 4'b1111;
		seletor = 3'b010;
		#DELAY;


		A = 4'b0011;
		B = 4'b0101;
		seletor = 3'b011;
		#DELAY;

		A = 4'b1010;
		B = 4'b1100;
		seletor = 3'b011;
		#DELAY;

		A = 4'b0110;
		B = 4'b0011;
		seletor = 3'b011;
		#DELAY;


		A = 4'b1111;
		B = 4'b0000;
		seletor = 3'b100;
		#DELAY;

		A = 4'b1010;
		B = 4'b1111;
		seletor = 3'b100;
		#DELAY;

		A = 4'b0101;
		B = 4'b1100;
		seletor = 3'b100;
		#DELAY;


		A = 4'b0001;
		B = 4'b0010;
		seletor = 3'b101;
		#DELAY;

		A = 4'b1111;
		B = 4'b0001;
		seletor = 3'b101;
		#DELAY;

		A = 4'b1000;
		B = 4'b0111;
		seletor = 3'b101;
		#DELAY;


		A = 4'b0001;
		B = 4'b0010;
		seletor = 3'b110;
		#DELAY;

		A = 4'b1111;
		B = 4'b0001;
		seletor = 3'b110;
		#DELAY;

		A = 4'b1000;
		B = 4'b0111;
		seletor = 3'b110;
		#DELAY;

		A = 4'b0001;
		B = 4'b0010;
		seletor = 3'b111;
		#DELAY;

		A = 4'b1111;
		B = 4'b0001;
		seletor = 3'b111;
		#DELAY;

		A = 4'b1000;
		B = 4'b0111;
		seletor = 3'b111;
		#DELAY;

		$finish;

	end
endmodule

CIDI-Modulos/SD122-CIRC-DIGITAIS-I/SD122-Task-12/task-2/CIDI-SD122-A112-2.vcd
$date
	Fri Dec  5 16:00:25 2025
$end
$version
	Icarus Verilog
$end
$timescale
	1ps
$end
$scope module ula_shift_tb $end
$var wire 4 ! resultado [3:0] $end
$var parameter 32 " DELAY $end
$var reg 4 # A [3:0] $end
$var reg 4 $ B [3:0] $end
$var reg 3 % seletor [2:0] $end
$scope module UUT $end
$var wire 4 & A [3:0] $end
$var wire 4 ' B [3:0] $end
$var wire 3 ( sel [2:0] $end
$var reg 4 ) resultado [3:0] $end
$upscope $end
$upscope $end
$enddefinitions $end
$comment Show the parameter values. $end
$dumpall
b1010 "
$end
#0
$dumpvars
b0 )
b0 (
b0 '
b0 &
b0 %
b0 $
b0 #
b0 !
$end
#10000
b1 $
b1 '
b10 #
b10 &
#20000
b1000 !
b1000 )
b1010 $
b1010 '
b1100 #
b1100 &
#30000
b111 !
b111 )
b1 %
b1 (
b11 $
b11 '
b101 #
b101 &
#40000
b1111 !
b1111 )
b1 $
b1 '
b1111 #
b1111 &
#50000
b1001 !
b1001 )
b1001 $
b1001 '
b1001 #
b1001 &
#60000
b1100 !
b1100 )
b10 %
b10 (
b1 $
b1 '
b11 #
b11 &
#70000
b1010 !
b1010 )
b101 $
b101 '
b101 #
b101 &
#80000
b0 !
b0 )
b1111 $
b1111 '
b1111 #
b1111 &
#90000
b1110 !
b1110 )
b11 %
b11 (
b101 $
b101 '
b11 #
b11 &
#100000
b111 !
b111 )
b1100 $
b1100 '
b1010 #
b1010 &
#110000
b1101 !
b1101 )
b11 $
b11 '
b110 #
b110 &
#120000
b1111 !
b1111 )
b100 %
b100 (
b0 $
b0 '
b1111 #
b1111 &
#130000
b1001 !
b1001 )
b1111 $
b1111 '
b1010 #
b1010 &
#140000
b1 !
b1 )
b1100 $
b1100 '
b101 #
b101 &
#150000
b1111 !
b1111 )
b101 %
b101 (
b10 $
b10 '
b1 #
b1 &
#160000
b1110 !
b1110 )
b1 $
b1 '
b1111 #
b1111 &
#170000
b1 !
b1 )
b111 $
b111 '
b1000 #
b1000 &
#180000
b10 !
b10 )
b110 %
b110 (
b10 $
b10 '
b1 #
b1 &
#190000
b1110 !
b1110 )
b1 $
b1 '
b1111 #
b1111 &
#200000
b0 !
b0 )
b111 $
b111 '
b1000 #
b1000 &
#210000
b111 %
b111 (
b10 $
b10 '
b1 #
b1 &
#220000
b111 !
b111 )
b1 $
b1 '
b1111 #
b1111 &
#230000
b100 !
b100 )
b111 $
b111 '
b1000 #
b1000 &
