CIDI-Modulos/SD112-INTRO-VERILOG/SD112-Task-14/demux_3x8.v
/*
Program: CI Digital 02/2025
Class: Introdução à Verilog  
Class-ID: D112
Advisor: Felipe Rocha 
Advisor-Contact: felipef.rocha@inatel.br
Institute: INATEL - Santa Rita do Sapucaí / MG  
Development: André Bezerra 
Student-Contact: andrefrbezerra@gmail.com
Task-ID: A-014
Type: Laboratory
Data: octuber, 17 2025
*/

`timescale 1 ns / 1 ps;

module demux_3x8 ( // #(parameter N = 3, M = 8)(
    input  [2:0] in,
    output reg [7:0] out
 );

    task demux(
        input  [2:0] in_data,
        output [7:0] out_data
     );
        begin
            out_data = 8'b0;         
            out_data[in_data] = 1'b1; 
        end
    endtask

    always @(*) begin // always demux(in, out);
        demux(in, out);
    end

endmodule

CIDI-Modulos/SD112-INTRO-VERILOG/SD112-Task-14/demux_3x8_tb.v
/*
Program: CI Digital 02/2025
Class: Introdução à Verilog  
Class-ID: SD112
Advisor: Felipe Rocha 
Advisor-Contact: felipef.rocha@inatel.br
Institute: INATEL - Santa Rita do Sapucaí / MG  
Development: André Bezerra 
Student-Contact: andrefrbezerra@gmail.com
Task-ID: A-014
Type: Testbench
Data: octuber, 17 2025
*/

`timescale 1 ns / 1 ps;
module demux_3x8_tb;

	localparam DELAY = 10;
    	reg [2:0] in;
    	wire [7:0] out;

    	demux_3x8 U1 (
        	.in(in),
        	.out(out)
    	);

	initial begin
    
		// Specify the VCD file name
		$dumpfile("CIDI-SD112-A014-3-dmux.vcd"); 
		$dumpvars(0, demux_3x8_tb); 
			
		$display("|Input	|Ouput	  |");
		$monitor("|%b	|%b |", in, out);
			
		in = 3'b000;
		#DELAY

		in = 3'b001;
		#DELAY

		in = 3'b010;
		#DELAY

		in = 3'b011;
		#DELAY

		in = 3'b100;
		#DELAY

		in = 3'b101; 
		#DELAY

		in = 3'b110; 
		#DELAY

		in = 3'b111; 
		#DELAY

		#DELAY 
		$finish; 
	end

endmodule

CIDI-Modulos/SD112-INTRO-VERILOG/SD112-Task-14/CIDI-SD112-A014-3-dmux.vcd
$date
	Sun Nov 23 11:32:32 2025
$end
$version
	Icarus Verilog
$end
$timescale
	1ps
$end
$scope module demux_3x8_tb $end
$var wire 8 ! out [7:0] $end
$var parameter 32 " DELAY $end
$var reg 3 # in [2:0] $end
$scope module U1 $end
$var wire 3 $ in [2:0] $end
$var reg 8 % out [7:0] $end
$scope task demux $end
$var reg 3 & in_data [2:0] $end
$var reg 8 ' out_data [7:0] $end
$upscope $end
$upscope $end
$upscope $end
$enddefinitions $end
$comment Show the parameter values. $end
$dumpall
b1010 "
$end
#0
$dumpvars
b1 '
b0 &
b1 %
b0 $
b0 #
b1 !
$end
#10000
b10 !
b10 %
b10 '
b1 &
b1 #
b1 $
#20000
b100 !
b100 %
b100 '
b10 &
b10 #
b10 $
#30000
b1000 !
b1000 %
b1000 '
b11 &
b11 #
b11 $
#40000
b10000 !
b10000 %
b10000 '
b100 &
b100 #
b100 $
#50000
b100000 !
b100000 %
b100000 '
b101 &
b101 #
b101 $
#60000
b1000000 !
b1000000 %
b1000000 '
b110 &
b110 #
b110 $
#70000
b10000000 !
b10000000 %
b10000000 '
b111 &
b111 #
b111 $
