CIDI-Modulos/SD122-CIRC-DIGITAIS-I/SD122-Task-3/exercicio_3/decoder_8x3.v
module decoder_8x3(
    input [7:0] in,
    output reg [2:0] out
);
    always @(*) begin
        casex(in)
            8'b00000001 : out = 3'b000;
            8'b00000010 : out = 3'b001;
            8'b00000100 : out = 3'b010;
            8'b00001000 : out = 3'b011;
            8'b00010000 : out = 3'b100;
            8'b00100000 : out = 3'b101;
            8'b01000000 : out = 3'b110;
            8'b10000000 : out = 3'b111;
            default     : out = 3'bxxx;
        endcase
    end

endmodule

module top(
    input [15:0] in,
    output [3:0] out
);
    
    wire [2:0] low_out;
    wire [2:0] high_out;
    wire high_active;

    decoder_8x3 dec_low(
        .in(in[7:0]),
        .out(low_out)
    );

    decoder_8x3 dec_high(
        .in(in[15:8]),
        .out(high_out)
    );

    assign high_active = |in[15:8];
    assign out = high_active ? {1'b1, high_out} : {1'b0, low_out};

endmodule

CIDI-Modulos/SD122-CIRC-DIGITAIS-I/SD122-Task-3/exercicio_3/decoder_8x3_tb.v
`timescale 1ns/1ps
`include "decoder_8x3.v"

module decoder_8x3_tb;

    reg [15:0] in;
    wire [3:0] out;

    // Instancia do módulo topo
    top uut(
        .in(in),
        .out(out)
    );

    initial begin
        $dumpfile("decoder_8x3_tb.vcd");
        $dumpvars(0, decoder_8x3_tb);

        // Testando todos os bits
        in = 16'b0000000000000001; #10;
        in = 16'b0000000000000010; #10;
        in = 16'b0000000000000100; #10;
        in = 16'b0000000000001000; #10;
        in = 16'b0000000000010000; #10;
        in = 16'b0000000000100000; #10;
        in = 16'b0000000001000000; #10;
        in = 16'b0000000010000000; #10;
        in = 16'b0000000100000000; #10;
        in = 16'b0000001000000000; #10;
        in = 16'b0000010000000000; #10;
        in = 16'b0000100000000000; #10;
        in = 16'b0001000000000000; #10;
        in = 16'b0010000000000000; #10;
        in = 16'b0100000000000000; #10;
        in = 16'b1000000000000000; #10;

        $finish;
    end

endmodule

CIDI-Modulos/SD122-CIRC-DIGITAIS-I/SD122-Task-3/exercicio_3/decoder_8x3_tb.vcd
$date
	Sun Nov  2 23:28:41 2025
$end
$version
	Icarus Verilog
$end
$timescale
	1ps
$end
$scope module decoder_8x3_tb $end
$var wire 4 ! out [3:0] $end
$var reg 16 " in [15:0] $end
$scope module uut $end
$var wire 16 # in [15:0] $end
$var wire 4 $ out [3:0] $end
$var wire 3 % low_out [2:0] $end
$var wire 3 & high_out [2:0] $end
$var wire 1 ' high_active $end
$scope module dec_high $end
$var wire 8 ( in [7:0] $end
$var reg 3 ) out [2:0] $end
$upscope $end
$scope module dec_low $end
$var wire 8 * in [7:0] $end
$var reg 3 + out [2:0] $end
$upscope $end
$upscope $end
$upscope $end
$enddefinitions $end
#0
$dumpvars
b0 +
b1 *
bx )
b0 (
0'
bx &
b0 %
b0 $
b1 #
b1 "
b0 !
$end
#10000
b1 !
b1 $
b1 %
b1 +
b10 *
b10 "
b10 #
#20000
b10 !
b10 $
b10 %
b10 +
b100 *
b100 "
b100 #
#30000
b11 !
b11 $
b11 %
b11 +
b1000 *
b1000 "
b1000 #
#40000
b100 !
b100 $
b100 %
b100 +
b10000 *
b10000 "
b10000 #
#50000
b101 !
b101 $
b101 %
b101 +
b100000 *
b100000 "
b100000 #
#60000
b110 !
b110 $
b110 %
b110 +
b1000000 *
b1000000 "
b1000000 #
#70000
b111 !
b111 $
b111 %
b111 +
b10000000 *
b10000000 "
b10000000 #
#80000
bx %
bx +
b0 &
b0 )
b1000 !
b1000 $
b0 *
b1 (
1'
b100000000 "
b100000000 #
#90000
b1001 !
b1001 $
b1 &
b1 )
b10 (
b1000000000 "
b1000000000 #
#100000
b1010 !
b1010 $
b10 &
b10 )
b100 (
b10000000000 "
b10000000000 #
#110000
b1011 !
b1011 $
b11 &
b11 )
b1000 (
b100000000000 "
b100000000000 #
#120000
b1100 !
b1100 $
b100 &
b100 )
b10000 (
b1000000000000 "
b1000000000000 #
#130000
b1101 !
b1101 $
b101 &
b101 )
b100000 (
b10000000000000 "
b10000000000000 #
#140000
b1110 !
b1110 $
b110 &
b110 )
b1000000 (
b100000000000000 "
b100000000000000 #
#150000
b1111 !
b1111 $
b111 &
b111 )
b10000000 (
b1000000000000000 "
b1000000000000000 #
