CIDI-Modulos/SD122-CIRC-DIGITAIS-I/SD122-Task-2/A102-1/task-3/bin_to_grey.v
/*
Program: CI Digital T2/2025
Class: Introdução à Verilog  
Class-ID: SD122
Advisor: Felipe Rocha 
Advisor-Contact: felipef.rocha@inatel.br
Institute: INATEL - Santa Rita do Sapucaí / MG  
Development: André Bezerra 
Student-Contact: andrefrbezerra@gmail.com
Task-ID: A-102-1
Type: Laboratory
Data: octuber, 17 2025
*/

`timescale 1 ns / 1 ps;

/*
	G3 = B3
	G2 = B3 ⊕ B2
	G1 = B2 ⊕ B1
	G0 = B1 ⊕ B0
*/

module bin_to_grey(
	input b3, b2, b1, b0, // [3:0] b
	output g3, g2, g1, g0 // [3:0] g
);
	// genvar i; 
	// generative ... 
	//	for(; < limit-1;) assign g[] = b[i+1] ^ b[i]
	// endgenerative
	assign g3 = b3;
	assign g2 = b3 ^ b2;
	assign g1 = b2 ^ b1;
	assign g0 = b1 ^ b0;

endmodule

CIDI-Modulos/SD122-CIRC-DIGITAIS-I/SD122-Task-2/A102-1/task-3/bin_to_grey_tb.v
/*
Program: CI Digital T2/2025
Class: Introdução à Verilog  
Class-ID: SD122
Advisor: Felipe Rocha 
Advisor-Contact: felipef.rocha@inatel.br
Institute: INATEL - Santa Rita do Sapucaí / MG  
Development: André Bezerra 
Student-Contact: andrefrbezerra@gmail.com
Task-ID: A-102-1
Type: Testbench
Data: octuber, 17 2025
*/

`timescale 1 ns / 1 ps;

module bin_to_grey_tb ();
    
	localparam DELAY = 10, SAMPLES = 16;
	reg b0, b1, b2, b3;  // [3:0] b
	wire g0, g1, g2, g3; // [3:0] g
	integer i;

	bin_to_grey UUT (
        	.b0(b0), .b1(b1), .b2(b2), .b3(b3),
        	.g0(g0), .g1(g1), .g2(g2), .g3(g3)
	);

	initial begin
        
        	$dumpfile("CIDI-SD122-A102-1-3.vcd");
		$dumpvars(0, bin_to_grey_tb);

		$display("|b3 b2 b1 b0	|g3 g2 g1 g0	|");
		$monitor("|%b %b %b %b	|%b %b %b %b	|", b3, b2, b1, b0, g3, g2, g1, g0);

		for (i = 0; i < SAMPLES; i = i + 1) begin
		    {b3, b2, b1, b0} = i;  // atribuindo valor binário
		    #DELAY;                     // espera 10 ns
		end

		$finish;
	end

endmodule

CIDI-Modulos/SD122-CIRC-DIGITAIS-I/SD122-Task-2/A102-1/task-3/CIDI-SD122-A102-1-3.vcd
$date
	Mon Nov 24 10:42:58 2025
$end
$version
	Icarus Verilog
$end
$timescale
	1ps
$end
$scope module bin_to_grey_tb $end
$var wire 1 ! g3 $end
$var wire 1 " g2 $end
$var wire 1 # g1 $end
$var wire 1 $ g0 $end
$var parameter 32 % DELAY $end
$var parameter 32 & SAMPLES $end
$var reg 1 ' b0 $end
$var reg 1 ( b1 $end
$var reg 1 ) b2 $end
$var reg 1 * b3 $end
$var integer 32 + i [31:0] $end
$scope module UUT $end
$var wire 1 ' b0 $end
$var wire 1 ( b1 $end
$var wire 1 ) b2 $end
$var wire 1 * b3 $end
$var wire 1 $ g0 $end
$var wire 1 # g1 $end
$var wire 1 " g2 $end
$var wire 1 ! g3 $end
$upscope $end
$upscope $end
$enddefinitions $end
$comment Show the parameter values. $end
$dumpall
b10000 &
b1010 %
$end
#0
$dumpvars
b0 +
0*
0)
0(
0'
0$
0#
0"
0!
$end
#10000
1$
1'
b1 +
#20000
1#
1(
0'
b10 +
#30000
0$
1'
b11 +
#40000
1"
1)
0(
0'
b100 +
#50000
1$
1'
b101 +
#60000
0#
1(
0'
b110 +
#70000
0$
1'
b111 +
#80000
1!
1*
0)
0(
0'
b1000 +
#90000
1$
1'
b1001 +
#100000
1#
1(
0'
b1010 +
#110000
0$
1'
b1011 +
#120000
0"
1)
0(
0'
b1100 +
#130000
1$
1'
b1101 +
#140000
0#
1(
0'
b1110 +
#150000
0$
1'
b1111 +
#160000
b10000 +
