CIDI-Modulos/SD142-CIRC-DIGITAIS-III/A-301/Task-5/rom_single_port.v
/*
Program: CI Digital T2/2025
Class: Circuito Digitais III
Class-ID: SD142
Advisor: Felipe Rocha 
Advisor-Contact: felipef.rocha@inatel.br
Institute: INATEL - Santa Rita do Sapucaí / MG  
Development: André Bezerra 
Student-Contact: andrefrbezerra@gmail.com
Task-ID: A-301 (A-301-T5)
Type: Laboratory
Data: febuary, 2 2026
*/

module single_port_rom #(
	parameter	DATA_WIDTH = 8,
				ADDR_WIDTH = 8
)(
	input 							clk,
	input 		[ADDR_WIDTH-1 : 0]	addr,
	output reg	[DATA_WIDTH-1 : 0]	q
);

	localparam SAMPLES = 2**ADDR_WIDTH; 

	reg [DATA_WIDTH-1:0] rom [SAMPLES-1:0];

	initial begin
		$readmemb("rom_single_port_init.txt", rom);
	end

	always @ (posedge clk) begin
		q <= rom[addr];
	end

endmodule

CIDI-Modulos/SD142-CIRC-DIGITAIS-III/A-301/Task-5/rom_single_port_tb.v

module single_port_rom_tb;

  // Parameters
  localparam	DATA_WIDTH	= 8,
  				ADDR_WIDTH	= 6,
  				DELAY		= 10;
  				SAMPLES		= 2**ADDR_WIDTH;

  //Ports
  reg	[ADDR_WIDTH-1 : 0]	addr;
  reg						clk;
  wire	[DATA_WIDTH-1 : 0]	q;

	single_port_rom 
	#(
		.DATA_WIDTH(DATA_WIDTH),
		.ADDR_WIDTH(ADDR_WIDTH)
	)
	UUT (
		.addr(addr),
		.clk(clk),
		.q(q)
	);

	always #(DELAY/2)  clk = ! clk;

	integer seed,i; 

	always @(posedge clk) seed = $time;

	initial begin
		
		clk = 1'b0;
		#(DELAY*5);
		
		for (i = 0; i < (SAMPLES); i = i + 1) begin
			addr <= $random(seed);
			@(posedge clk);

			// display

			#DELAY;
		end

		$finish;
	end

endmodule

CIDI-Modulos/SD142-CIRC-DIGITAIS-III/A-301/Task-5/CIDI-SD142-A301-rom.vcd
$date
	Mon Feb 23 01:57:11 2026
$end
$version
	Icarus Verilog
$end
$timescale
	1s
$end
$scope module single_port_rom_tb $end
$var wire 8 ! q [7:0] $end
$var parameter 32 " ADDR_WIDTH $end
$var parameter 32 # DATA_WIDTH $end
$var parameter 32 $ DELAY $end
$var parameter 32 % SAMPLES $end
$var reg 6 & addr [5:0] $end
$var reg 1 ' clk $end
$var integer 32 ( i [31:0] $end
$var integer 32 ) seed [31:0] $end
$scope module UUT $end
$var wire 6 * addr [5:0] $end
$var wire 1 ' clk $end
$var parameter 32 + ADDR_WIDTH $end
$var parameter 32 , DATA_WIDTH $end
$var parameter 32 - SAMPLES $end
$var reg 8 . q [7:0] $end
$upscope $end
$upscope $end
$enddefinitions $end
$comment Show the parameter values. $end
$dumpall
b1000000 -
b1000 ,
b110 +
b1000000 %
b1100100 $
b1000 #
b110 "
$end
#0
$dumpvars
bx .
bx *
bx )
bx (
0'
bx &
bx !
$end
#10
b1010 )
1'
#20
b0 &
b0 *
0'
b10101000101000000011 )
b0 (
#30
b10000000 !
b10000000 .
b11110 )
1'
#40
0'
#50
b110010 )
1'
#60
0'
#70
b1000110 )
1'
#80
0'
#90
b1011010 )
1'
#100
0'
#110
b1101110 )
1'
#120
0'
#130
1'
b10000010 )
b1 (
#140
0'
#150
b10010110 )
1'
#160
0'
#170
b10101010 )
1'
#180
0'
#190
b10111110 )
1'
#200
0'
#210
b11010010 )
1'
#220
0'
#230
b1 &
b1 *
1'
b11100110 )
b10 (
#240
0'
#250
b11111010 )
1'
#260
0'
#270
b100001110 )
1'
#280
0'
#290
b100100010 )
1'
#300
0'
#310
b100110110 )
1'
#320
0'
#330
b10 &
b10 *
1'
b101001010 )
b11 (
#340
0'
#350
b101011110 )
1'
#360
0'
#370
b101110010 )
1'
#380
0'
#390
b110000110 )
1'
#400
0'
#410
b110011010 )
1'
#420
0'
#430
b11 &
b11 *
1'
b110101110 )
b100 (
#440
0'
#450
b111000010 )
1'
#460
0'
#470
b111010110 )
1'
#480
0'
#490
b111101010 )
1'
#500
0'
#510
b111111110 )
1'
#520
0'
#530
b100 &
b100 *
1'
b1000010010 )
b101 (
#540
0'
#550
b1000100110 )
1'
#560
0'
#570
b1000111010 )
1'
#580
0'
#590
b1001001110 )
1'
#600
0'
#610
b1001100010 )
1'
#620
0'
#630
b101 &
b101 *
1'
b1001110110 )
b110 (
#640
0'
#650
b1010001010 )
1'
#660
0'
#670
b1010011110 )
1'
#680
0'
#690
b1010110010 )
1'
#700
0'
#710
b1011000110 )
1'
#720
0'
#730
1'
b1011011010 )
b111 (
#740
0'
#750
b1011101110 )
1'
#760
0'
#770
b1100000010 )
1'
#780
0'
#790
b1100010110 )
1'
#800
0'
#810
b1100101010 )
1'
#820
0'
#830
b110 &
b110 *
1'
b1100111110 )
b1000 (
#840
0'
#850
b1000000 !
b1000000 .
b1101010010 )
1'
#860
0'
#870
b1101100110 )
1'
#880
0'
#890
b1101111010 )
1'
#900
0'
#910
b1110001110 )
1'
#920
0'
#930
b111 &
b111 *
1'
b1110100010 )
b1001 (
#940
0'
#950
b1110110110 )
1'
#960
0'
#970
b1111001010 )
1'
#980
0'
#990
b1111011110 )
1'
#1000
0'
#1010
b1111110010 )
1'
#1020
0'
#1030
b1000 &
b1000 *
1'
b10000000110 )
b1010 (
#1040
0'
#1050
b10000011010 )
1'
#1060
0'
#1070
b10000101110 )
1'
#1080
0'
#1090
b10001000010 )
1'
#1100
0'
#1110
b10001010110 )
1'
#1120
0'
#1130
b1001 &
b1001 *
1'
b10001101010 )
b1011 (
#1140
0'
#1150
b10001111110 )
1'
#1160
0'
#1170
b10010010010 )
1'
#1180
0'
#1190
b10010100110 )
1'
#1200
0'
#1210
b10010111010 )
1'
#1220
0'
#1230
1'
b10011001110 )
b1100 (
#1240
0'
#1250
b10011100010 )
1'
#1260
0'
#1270
b10011110110 )
1'
#1280
0'
#1290
b10100001010 )
1'
#1300
0'
#1310
b10100011110 )
1'
#1320
0'
#1330
b1010 &
b1010 *
1'
b10100110010 )
b1101 (
#1340
0'
#1350
b10101000110 )
1'
#1360
0'
#1370
b10101011010 )
1'
#1380
0'
#1390
b10101101110 )
1'
#1400
0'
#1410
b10110000010 )
1'
#1420
0'
#1430
b1011 &
b1011 *
1'
b10110010110 )
b1110 (
#1440
0'
#1450
b10110101010 )
1'
#1460
0'
#1470
b10110111110 )
1'
#1480
0'
#1490
b10111010010 )
1'
#1500
0'
#1510
b10111100110 )
1'
#1520
0'
#1530
b1100 &
b1100 *
1'
b10111111010 )
b1111 (
#1540
0'
#1550
b100000 !
b100000 .
b11000001110 )
1'
#1560
0'
#1570
b11000100010 )
1'
#1580
0'
#1590
b11000110110 )
1'
#1600
0'
#1610
b11001001010 )
1'
#1620
0'
#1630
b1101 &
b1101 *
1'
b11001011110 )
b10000 (
#1640
0'
#1650
b11001110010 )
1'
#1660
0'
#1670
b11010000110 )
1'
#1680
0'
#1690
b11010011010 )
1'
#1700
0'
#1710
b11010101110 )
1'
#1720
0'
#1730
b1110 &
b1110 *
1'
b11011000010 )
b10001 (
#1740
0'
#1750
b11011010110 )
1'
#1760
0'
#1770
b11011101010 )
1'
#1780
0'
#1790
b11011111110 )
1'
#1800
0'
#1810
b11100010010 )
1'
#1820
0'
#1830
1'
b11100100110 )
b10010 (
#1840
0'
#1850
b11100111010 )
1'
#1860
0'
#1870
b11101001110 )
1'
#1880
0'
#1890
b11101100010 )
1'
#1900
0'
#1910
b11101110110 )
1'
#1920
0'
#1930
b1111 &
b1111 *
1'
b11110001010 )
b10011 (
#1940
0'
#1950
b11110011110 )
1'
#1960
0'
#1970
b11110110010 )
1'
#1980
0'
#1990
b11111000110 )
1'
#2000
0'
#2010
b11111011010 )
1'
#2020
0'
#2030
b10000 &
b10000 *
1'
b11111101110 )
b10100 (
#2040
0'
#2050
b100000000010 )
1'
#2060
0'
#2070
b100000010110 )
1'
#2080
0'
#2090
b100000101010 )
1'
#2100
0'
#2110
b100000111110 )
1'
#2120
0'
#2130
b10001 &
b10001 *
1'
b100001010010 )
b10101 (
#2140
0'
#2150
b100001100110 )
1'
#2160
0'
#2170
b100001111010 )
1'
#2180
0'
#2190
b100010001110 )
1'
#2200
0'
#2210
b100010100010 )
1'
#2220
0'
#2230
b10010 &
b10010 *
1'
b100010110110 )
b10110 (
#2240
0'
#2250
b10000 !
b10000 .
b100011001010 )
1'
#2260
0'
#2270
b100011011110 )
1'
#2280
0'
#2290
b100011110010 )
1'
#2300
0'
#2310
b100100000110 )
1'
#2320
0'
#2330
b10011 &
b10011 *
1'
b100100011010 )
b10111 (
#2340
0'
#2350
b100100101110 )
1'
#2360
0'
#2370
b100101000010 )
1'
#2380
0'
#2390
b100101010110 )
1'
#2400
0'
#2410
b100101101010 )
1'
#2420
0'
#2430
1'
b100101111110 )
b11000 (
#2440
0'
#2450
b100110010010 )
1'
#2460
0'
#2470
b100110100110 )
1'
#2480
0'
#2490
b100110111010 )
1'
#2500
0'
#2510
b100111001110 )
1'
#2520
0'
#2530
b10100 &
b10100 *
1'
b100111100010 )
b11001 (
#2540
0'
#2550
b100111110110 )
1'
#2560
0'
#2570
b101000001010 )
1'
#2580
0'
#2590
b101000011110 )
1'
#2600
0'
#2610
b101000110010 )
1'
#2620
0'
#2630
b10101 &
b10101 *
1'
b101001000110 )
b11010 (
#2640
0'
#2650
b101001011010 )
1'
#2660
0'
#2670
b101001101110 )
1'
#2680
0'
#2690
b101010000010 )
1'
#2700
0'
#2710
b101010010110 )
1'
#2720
0'
#2730
b10110 &
b10110 *
1'
b101010101010 )
b11011 (
#2740
0'
#2750
b101010111110 )
1'
#2760
0'
#2770
b101011010010 )
1'
#2780
0'
#2790
b101011100110 )
1'
#2800
0'
#2810
b101011111010 )
1'
#2820
0'
#2830
b10111 &
b10111 *
1'
b101100001110 )
b11100 (
#2840
0'
#2850
b101100100010 )
1'
#2860
0'
#2870
b101100110110 )
1'
#2880
0'
#2890
b101101001010 )
1'
#2900
0'
#2910
b101101011110 )
1'
#2920
0'
#2930
1'
b101101110010 )
b11101 (
#2940
0'
#2950
b101110000110 )
1'
#2960
0'
#2970
b101110011010 )
1'
#2980
0'
#2990
b101110101110 )
1'
#3000
0'
#3010
b101111000010 )
1'
#3020
0'
#3030
b11000 &
b11000 *
1'
b101111010110 )
b11110 (
#3040
0'
#3050
b1000 !
b1000 .
b101111101010 )
1'
#3060
0'
#3070
b101111111110 )
1'
#3080
0'
#3090
b110000010010 )
1'
#3100
0'
#3110
b110000100110 )
1'
#3120
0'
#3130
b11001 &
b11001 *
1'
b110000111010 )
b11111 (
#3140
0'
#3150
b110001001110 )
1'
#3160
0'
#3170
b110001100010 )
1'
#3180
0'
#3190
b110001110110 )
1'
#3200
0'
#3210
b110010001010 )
1'
#3220
0'
#3230
b11010 &
b11010 *
1'
b110010011110 )
b100000 (
#3240
0'
#3250
b110010110010 )
1'
#3260
0'
#3270
b110011000110 )
1'
#3280
0'
#3290
b110011011010 )
1'
#3300
0'
#3310
b110011101110 )
1'
#3320
0'
#3330
b11011 &
b11011 *
1'
b110100000010 )
b100001 (
#3340
0'
#3350
b110100010110 )
1'
#3360
0'
#3370
b110100101010 )
1'
#3380
0'
#3390
b110100111110 )
1'
#3400
0'
#3410
b110101010010 )
1'
#3420
0'
#3430
b11100 &
b11100 *
1'
b110101100110 )
b100010 (
#3440
0'
#3450
b110101111010 )
1'
#3460
0'
#3470
b110110001110 )
1'
#3480
0'
#3490
b110110100010 )
1'
#3500
0'
#3510
b110110110110 )
1'
#3520
0'
#3530
1'
b110111001010 )
b100011 (
#3540
0'
#3550
b110111011110 )
1'
#3560
0'
#3570
b110111110010 )
1'
#3580
0'
#3590
b111000000110 )
1'
#3600
0'
#3610
b111000011010 )
1'
#3620
0'
#3630
b11101 &
b11101 *
1'
b111000101110 )
b100100 (
#3640
0'
#3650
b111001000010 )
1'
#3660
0'
#3670
b111001010110 )
1'
#3680
0'
#3690
b111001101010 )
1'
#3700
0'
#3710
b111001111110 )
1'
#3720
0'
#3730
b11110 &
b11110 *
1'
b111010010010 )
b100101 (
#3740
0'
#3750
b100 !
b100 .
b111010100110 )
1'
#3760
0'
#3770
b111010111010 )
1'
#3780
0'
#3790
b111011001110 )
1'
#3800
0'
#3810
b111011100010 )
1'
#3820
0'
#3830
b11111 &
b11111 *
1'
b111011110110 )
b100110 (
#3840
0'
#3850
b111100001010 )
1'
#3860
0'
#3870
b111100011110 )
1'
#3880
0'
#3890
b111100110010 )
1'
#3900
0'
#3910
b111101000110 )
1'
#3920
0'
#3930
b100000 &
b100000 *
1'
b111101011010 )
b100111 (
#3940
0'
#3950
b111101101110 )
1'
#3960
0'
#3970
b111110000010 )
1'
#3980
0'
#3990
b111110010110 )
1'
#4000
0'
#4010
b111110101010 )
1'
#4020
0'
#4030
b100001 &
b100001 *
1'
b111110111110 )
b101000 (
#4040
0'
#4050
b111111010010 )
1'
#4060
0'
#4070
b111111100110 )
1'
#4080
0'
#4090
b111111111010 )
1'
#4100
0'
#4110
b1000000001110 )
1'
#4120
0'
#4130
1'
b1000000100010 )
b101001 (
#4140
0'
#4150
b1000000110110 )
1'
#4160
0'
#4170
b1000001001010 )
1'
#4180
0'
#4190
b1000001011110 )
1'
#4200
0'
#4210
b1000001110010 )
1'
#4220
0'
#4230
b100010 &
b100010 *
1'
b1000010000110 )
b101010 (
#4240
0'
#4250
b1000010011010 )
1'
#4260
0'
#4270
b1000010101110 )
1'
#4280
0'
#4290
b1000011000010 )
1'
#4300
0'
#4310
b1000011010110 )
1'
#4320
0'
#4330
b100011 &
b100011 *
1'
b1000011101010 )
b101011 (
#4340
0'
#4350
b10 !
b10 .
b1000011111110 )
1'
#4360
0'
#4370
b1000100010010 )
1'
#4380
0'
#4390
b1000100100110 )
1'
#4400
0'
#4410
b1000100111010 )
1'
#4420
0'
#4430
b100100 &
b100100 *
1'
b1000101001110 )
b101100 (
#4440
0'
#4450
b1000101100010 )
1'
#4460
0'
#4470
b1000101110110 )
1'
#4480
0'
#4490
b1000110001010 )
1'
#4500
0'
#4510
b1000110011110 )
1'
#4520
0'
#4530
b100101 &
b100101 *
1'
b1000110110010 )
b101101 (
#4540
0'
#4550
b1000111000110 )
1'
#4560
0'
#4570
b1000111011010 )
1'
#4580
0'
#4590
b1000111101110 )
1'
#4600
0'
#4610
b1001000000010 )
1'
#4620
0'
#4630
1'
b1001000010110 )
b101110 (
#4640
0'
#4650
b1001000101010 )
1'
#4660
0'
#4670
b1001000111110 )
1'
#4680
0'
#4690
b1001001010010 )
1'
#4700
0'
#4710
b1001001100110 )
1'
#4720
0'
#4730
b100110 &
b100110 *
1'
b1001001111010 )
b101111 (
#4740
0'
#4750
b1001010001110 )
1'
#4760
0'
#4770
b1001010100010 )
1'
#4780
0'
#4790
b1001010110110 )
1'
#4800
0'
#4810
b1001011001010 )
1'
#4820
0'
#4830
b100111 &
b100111 *
1'
b1001011011110 )
b110000 (
#4840
0'
#4850
b1001011110010 )
1'
#4860
0'
#4870
b1001100000110 )
1'
#4880
0'
#4890
b1001100011010 )
1'
#4900
0'
#4910
b1001100101110 )
1'
#4920
0'
#4930
b101000 &
b101000 *
1'
b1001101000010 )
b110001 (
#4940
0'
#4950
b1001101010110 )
1'
#4960
0'
#4970
b1001101101010 )
1'
#4980
0'
#4990
b1001101111110 )
1'
#5000
0'
#5010
b1001110010010 )
1'
#5020
0'
#5030
b101001 &
b101001 *
1'
b1001110100110 )
b110010 (
#5040
0'
#5050
b1 !
b1 .
b1001110111010 )
1'
#5060
0'
#5070
b1001111001110 )
1'
#5080
0'
#5090
b1001111100010 )
1'
#5100
0'
#5110
b1001111110110 )
1'
#5120
0'
#5130
b101010 &
b101010 *
1'
b1010000001010 )
b110011 (
#5140
0'
#5150
b1010000011110 )
1'
#5160
0'
#5170
b1010000110010 )
1'
#5180
0'
#5190
b1010001000110 )
1'
#5200
0'
#5210
b1010001011010 )
1'
#5220
0'
#5230
1'
b1010001101110 )
b110100 (
#5240
0'
#5250
b1010010000010 )
1'
#5260
0'
#5270
b1010010010110 )
1'
#5280
0'
#5290
b1010010101010 )
1'
#5300
0'
#5310
b1010010111110 )
1'
#5320
0'
#5330
b101011 &
b101011 *
1'
b1010011010010 )
b110101 (
#5340
0'
#5350
b1010011100110 )
1'
#5360
0'
#5370
b1010011111010 )
1'
#5380
0'
#5390
b1010100001110 )
1'
#5400
0'
#5410
b1010100100010 )
1'
#5420
0'
#5430
b101100 &
b101100 *
1'
b1010100110110 )
b110110 (
#5440
0'
#5450
b1010101001010 )
1'
#5460
0'
#5470
b1010101011110 )
1'
#5480
0'
#5490
b1010101110010 )
1'
#5500
0'
#5510
b1010110000110 )
1'
#5520
0'
#5530
b101101 &
b101101 *
1'
b1010110011010 )
b110111 (
#5540
0'
#5550
b1010110101110 )
1'
#5560
0'
#5570
b1010111000010 )
1'
#5580
0'
#5590
b1010111010110 )
1'
#5600
0'
#5610
b1010111101010 )
1'
#5620
0'
#5630
b101110 &
b101110 *
1'
b1010111111110 )
b111000 (
#5640
0'
#5650
b1011000010010 )
1'
#5660
0'
#5670
b1011000100110 )
1'
#5680
0'
#5690
b1011000111010 )
1'
#5700
0'
#5710
b1011001001110 )
1'
#5720
0'
#5730
b101111 &
b101111 *
1'
b1011001100010 )
b111001 (
#5740
0'
#5750
b0 !
b0 .
b1011001110110 )
1'
#5760
0'
#5770
b1011010001010 )
1'
#5780
0'
#5790
b1011010011110 )
1'
#5800
0'
#5810
b1011010110010 )
1'
#5820
0'
#5830
1'
b1011011000110 )
b111010 (
#5840
0'
#5850
b1011011011010 )
1'
#5860
0'
#5870
b1011011101110 )
1'
#5880
0'
#5890
b1011100000010 )
1'
#5900
0'
#5910
b1011100010110 )
1'
#5920
0'
#5930
b110000 &
b110000 *
1'
b1011100101010 )
b111011 (
#5940
0'
#5950
b1011100111110 )
1'
#5960
0'
#5970
b1011101010010 )
1'
#5980
0'
#5990
b1011101100110 )
1'
#6000
0'
#6010
b1011101111010 )
1'
#6020
0'
#6030
b110001 &
b110001 *
1'
b1011110001110 )
b111100 (
#6040
0'
#6050
b1011110100010 )
1'
#6060
0'
#6070
b1011110110110 )
1'
#6080
0'
#6090
b1011111001010 )
1'
#6100
0'
#6110
b1011111011110 )
1'
#6120
0'
#6130
b110010 &
b110010 *
1'
b1011111110010 )
b111101 (
#6140
0'
#6150
b1100000000110 )
1'
#6160
0'
#6170
b1100000011010 )
1'
#6180
0'
#6190
b1100000101110 )
1'
#6200
0'
#6210
b1100001000010 )
1'
#6220
0'
#6230
b110011 &
b110011 *
1'
b1100001010110 )
b111110 (
#6240
0'
#6250
b1100001101010 )
1'
#6260
0'
#6270
b1100001111110 )
1'
#6280
0'
#6290
b1100010010010 )
1'
#6300
0'
#6310
b1100010100110 )
1'
#6320
0'
#6330
1'
b1100010111010 )
b111111 (
#6340
0'
#6350
b1100011001110 )
1'
#6360
0'
#6370
b1100011100010 )
1'
#6380
0'
#6390
b1100011110110 )
1'
#6400
0'
#6410
b1100100001010 )
1'
#6420
0'
#6430
1'
b1000000 (
